Workbook

Sheet Instructions
A1: SVDP Comprehensive Excel Workbook
A3: Purpose | B3: Excel-first decision-support model for donated-goods space optimization, goods flow, and procurement analysis.
A4: How to present | B4: Start with Executive_Dashboard, then Flow_Dashboard, then Slotting_Dashboard. Use Recommendations last.
A5: What is editable | B5: Only yellow cells in Controls and any estimated quantities in Slotting_Model if you receive better counts.
A6: Key data sources | B6: General Ledger, uploaded invoices, monthly result workbooks, warehouse layout redesigns, and rack sketch.
A7: Important note | B7: Qty_Held values are planning assumptions so the model can run now. Update later if the client provides exact inventory.
A20: Important | B20: Open this workbook in Excel desktop and save once so all formulas and charts recalculate and display cached values correctly.

Sheet Executive_Dashboard
A1: SVDP Donated Goods Space Optimization – Executive Dashboard
A3: Project objective: | B3: Optimize space utilization and goods flow through slotting, bin classification, and warehouse redesign.
A5: Total Spend | D5: Capacity Increase | G5: Water Orders | J5: Est. Water Savings
A6: =Project_KPIs!B4 | D6: =Project_KPIs!B10 | G6: =Project_KPIs!B8 | J6: =Project_KPIs!B13
A9: Before vs After | F9: Key Insights
A10: Metric | B10: Before | C10: After / Impact | F10: • Water ordering is highly repetitive, indicating a contract opportunity.
A11: Pallet Capacity | B11: =Warehouse_Capacity!B8 | C11: =Warehouse_Capacity!C8 | F11: • Warehouse redesign uses the 4 uploaded layout files; quantified net pallet gain is 251 positions.
A12: Capacity Change | B12: - | C12: =Warehouse_Capacity!D8 | F12: • GIK delivers the strongest capacity gain and should support high-flow items.
A13: Capacity Change % | B13: - | C13: =Warehouse_Capacity!E8 | F13: • Slotting recommendations prioritize usage, flow, quantity received, quantity held, and item type.
A14: Water Spend | B14: - | C14: =Project_KPIs!B7 | F14: • Final plan applies a capacity constraint so only top-ranked items use premium locations; remaining items are distributed across FOOD, GIK, GARAGE/KITCHEN, and ADDITIONS.
F16: • The final reallocation plan now uses one consistent hybrid location logic across all slotting sheets.
H17: Month | I17: Net Spend ($)
H18: 45566 | I18: 63380.44
H19: 45597 | I19: 87215.87
H20: 45627 | I20: 62474.12
H21: 45658 | I21: 3561.6
H22: 45689 | I22: 3561.6
H23: 45717 | I23: 155712.6
H24: 45748 | I24: 74243.13
H25: 45809 | I25: 40638.24
H26: 45839 | I26: 136090.8
H27: 45870 | I27: 37459.2
H28: 45901 | I28: 61717.1

Sheet Flow_Dashboard
A1: Goods Flow Dashboard
A3: Monthly goods-flow view showing inbound volume, usable output, and processing losses (waste + RTV) to support slotting decisions.
A5: Total Inbound lbs | D5: Net Usable lbs | G5: Water Orders | J5: Net Capacity Gain
A6: =Monthly_Flow!I8 | D6: =Monthly_Flow!J8 | G6: =Project_KPIs!B8 | J6: =Project_KPIs!B10
A10: Month | B10: TEFAP Lbs | C10: Regular Receipts Lbs | D10: Food Drives Lbs | E10: Truck Log Lbs | F10: Receiving Sheet Lbs | G10: RTV Lbs | H10: Garbage Out Lbs | I10: Total Inbound Lbs | J10: Net Usable Lbs | L10: Month | M10: Inbound | N10: Net Usable | O10: Yield % | Q10: Month | R10: RTV | S10: Garbage
A11: Oct-2025 | B11: 1764 | C11: 89891 | D11: 0 | E11: 23795 | F11: 497495 | G11: 4728 | H11: 66380 | I11: 91655 | J11: 20547 | L11: =A11 | M11: =I11 | N11: =J11 | O11: =IFERROR(N11/M11,0) | Q11: =A11 | R11: =G11 | S11: =H11
A12: Nov-2025 | B12: 5890 | C12: 70232 | D12: 82211 | E12: 31749 | F12: 497066 | G12: 0 | H12: 43960 | I12: 158333 | J12: 114373 | L12: =A12 | M12: =I12 | N12: =J12 | O12: =IFERROR(N12/M12,0) | Q12: =A12 | R12: =G12 | S12: =H12
A13: Dec-2025 | B13: 10034 | C13: 60625 | D13: 60207 | E13: 24957 | F13: 435128 | G13: 0 | H13: 34980 | I13: 130866 | J13: 95886 | L13: =A13 | M13: =I13 | N13: =J13 | O13: =IFERROR(N13/M13,0) | Q13: =A13 | R13: =G13 | S13: =H13
A14: Jan-2026 | B14: 13180 | C14: 438120 | D14: 15600 | E14: 87625 | F14: 438120 | G14: 8178 | H14: 38600 | I14: 466900 | J14: 420122 | L14: =A14 | M14: =I14 | N14: =J14 | O14: =IFERROR(N14/M14,0) | Q14: =A14 | R14: =G14 | S14: =H14
W20: How to read this dashboard
W21: • Inbound vs Net Usable shows how much material actually becomes usable inventory.
W22: • Yield % indicates the efficiency of processing and handling.
W23: • RTV + Garbage highlights where losses reduce usable output.

Sheet Slotting_Dashboard
A1: Slotting & Goods-Flow Dashboard
A3: Dashboard shows current vs hybrid plan. Distribution inside each bucket now follows score rank, not row order.
A5: Items evaluated | D5: Moves / re-slots | G5: Premium items | J5: Reserve items
A6: =COUNTA(Slotting_Model!A4:A18) | D6: =COUNTIF(Slotting_Model!AJ4:AJ18,"<>Keep in place") | G6: =COUNTIF(Slotting_Model!AH4:AH18,"Premium") | J6: =COUNTIF(Slotting_Model!AH4:AH18,"Reserve")
A10: Item | B10: Current | C10: Hybrid_Location | D10: Score | E10: Hybrid_Reason | Q10: How to read this dashboard | Z10: How to read this dashboard
A11: =Slotting_Model!A4 | B11: =Slotting_Model!J4 | C11: =Slotting_Model!AO4 | D11: =Slotting_Model!X4 | E11: =Slotting_Model!AP4 | Q11: • Current = assumed existing location. | Z11: • Current shows the assumed existing location.
A12: =Slotting_Model!A5 | B12: =Slotting_Model!J5 | C12: =Slotting_Model!AO5 | D12: =Slotting_Model!X5 | E12: =Slotting_Model!AP5 | Q12: • Hybrid_Location = final practical location using your chosen ranking sequence. | Z12: • Depth-Optimized Plan shows the implementable location after capacity and 1/2/3 position balancing.
A13: =Slotting_Model!A6 | B13: =Slotting_Model!J6 | C13: =Slotting_Model!AO6 | D13: =Slotting_Model!X6 | E13: =Slotting_Model!AP6 | Q13: • The sequence used is A1, B1, C1, A2, B2, A3, B3, C2, C3. | Z13: • Premium items are no longer all assigned to the same A-front position.
A14: =Slotting_Model!A7 | B14: =Slotting_Model!J7 | C14: =Slotting_Model!AO7 | D14: =Slotting_Model!X7 | E14: =Slotting_Model!AP7 | Q14: • This logic is now used consistently in Slotting_Model, Storage_Reallocation_Plan, and Slotting_Dashboard. | Z14: • The 1 / 2 / 3 chart confirms the model is distributing storage positions more realistically.
A15: =Slotting_Model!A8 | B15: =Slotting_Model!J8 | C15: =Slotting_Model!AO8 | D15: =Slotting_Model!X8 | E15: =Slotting_Model!AP8
A16: =Slotting_Model!A9 | B16: =Slotting_Model!J9 | C16: =Slotting_Model!AO9 | D16: =Slotting_Model!X9 | E16: =Slotting_Model!AP9
A17: =Slotting_Model!A10 | B17: =Slotting_Model!J10 | C17: =Slotting_Model!AO10 | D17: =Slotting_Model!X10 | E17: =Slotting_Model!AP10
A18: =Slotting_Model!A11 | B18: =Slotting_Model!J11 | C18: =Slotting_Model!AO11 | D18: =Slotting_Model!X11 | E18: =Slotting_Model!AP11 | J18: Hybrid Logic Check
A19: =Slotting_Model!A12 | B19: =Slotting_Model!J12 | C19: =Slotting_Model!AO12 | D19: =Slotting_Model!X12 | E19: =Slotting_Model!AP12 | J19: Items are now ordered within each bucket by score rank.
A20: =Slotting_Model!A13 | B20: =Slotting_Model!J13 | C20: =Slotting_Model!AO13 | D20: =Slotting_Model!X13 | E20: =Slotting_Model!AP13 | J20: Higher-scoring Premium items take earlier hybrid positions.
A21: =Slotting_Model!A14 | B21: =Slotting_Model!J14 | C21: =Slotting_Model!AO14 | D21: =Slotting_Model!X14 | E21: =Slotting_Model!AP14 | J21: This removes dependence on row order.
A22: =Slotting_Model!A15 | B22: =Slotting_Model!J15 | C22: =Slotting_Model!AO15 | D22: =Slotting_Model!X15 | E22: =Slotting_Model!AP15
A23: =Slotting_Model!A16 | B23: =Slotting_Model!J16 | C23: =Slotting_Model!AO16 | D23: =Slotting_Model!X16 | E23: =Slotting_Model!AP16
A24: =Slotting_Model!A17 | B24: =Slotting_Model!J17 | C24: =Slotting_Model!AO17 | D24: =Slotting_Model!X17 | E24: =Slotting_Model!AP17
A25: =Slotting_Model!A18 | B25: =Slotting_Model!J18 | C25: =Slotting_Model!AO18 | D25: =Slotting_Model!X18 | E25: =Slotting_Model!AP18
A26: Capacity Bucket | B26: Count | G26: Capacity Bucket | H26: Count | J26: Preferred Area | K26: Count | M26: Pattern | N26: Count | Q26: Area | R26: Count
A27: Premium | B27: =COUNTIF(Slotting_Model!AH4:AH18,"Premium") | G27: Premium | H27: =COUNTIF(Slotting_Model!AH4:AH18,"Premium") | J27: GIK | K27: =COUNTIF(Slotting_Model!AG4:AG18,"GIK") | M27: A1 | N27: =COUNTIF(Slotting_Model!AO4:AO18,"*-A1-*") | Q27: GIK | R27: =COUNTIF(Slotting_Model!AG4:AG18,"GIK")
A28: Standard | B28: =COUNTIF(Slotting_Model!AH4:AH18,"Standard") | G28: Standard | H28: =COUNTIF(Slotting_Model!AH4:AH18,"Standard") | J28: FOOD | K28: =COUNTIF(Slotting_Model!AG4:AG18,"FOOD") | M28: B1 | N28: =COUNTIF(Slotting_Model!AO4:AO18,"*-B1-*") | P28: How to read this dashboard | Q28: FOOD | R28: =COUNTIF(Slotting_Model!AG4:AG18,"FOOD")
A29: Reserve | B29: =COUNTIF(Slotting_Model!AH4:AH18,"Reserve") | G29: Reserve | H29: =COUNTIF(Slotting_Model!AH4:AH18,"Reserve") | J29: GARAGE/KITCHEN | K29: =COUNTIF(Slotting_Model!AG4:AG18,"GARAGE/KITCHEN") | M29: C1 | N29: =COUNTIF(Slotting_Model!AO4:AO18,"*-C1-*") | P29: • Current shows where the item is assumed to be today. | Q29: GARAGE/KITCHEN | R29: =COUNTIF(Slotting_Model!AG4:AG18,"GARAGE/KITCHEN")
J30: ADDITIONS | K30: =COUNTIF(Slotting_Model!AG4:AG18,"ADDITIONS") | M30: A2 | N30: =COUNTIF(Slotting_Model!AO4:AO18,"*-A2-*") | P30: • Practical Plan shows the implementable location after applying capacity constraints. | Q30: ADDITIONS | R30: =COUNTIF(Slotting_Model!AG4:AG18,"ADDITIONS")
A31: Chart Check | M31: Other | N31: =COUNTA(Slotting_Model!AO4:AO18)-SUM(N27:N30) | P31: • Capacity Bucket shows which items get premium vs standard vs reserve storage.
A32: • Bar chart now uses the final Storage Priority Score column. | P32: • Preferred Area links each item to the most suitable warehouse area from the 4 uploaded layouts.
A33: • Pie chart now counts recommended A/B/C levels from the final model.
A34: • Dashboard table uses Current Location, Recommended Location, Score, and Reason from the updated Slotting_Model. | P34: • Capacity distribution chart now uses Premium / Standard / Reserve from the capacity-constrained plan.

Sheet Project_KPIs
A1: Project KPIs
A3: Metric | B3: Value | C3: Interpretation | D3: Source
A4: Total Spend ($) | B4: =SUM(Clean_Transactions!H:H) | C4: Spend observed in cleaned transaction ledger | D4: Clean_Transactions
A5: Food Spend ($) | B5: =SUMIF(Clean_Transactions!D:D,"Food",Clean_Transactions!H:H) | C5: Food procurement exposure | D5: Clean_Transactions
A6: Meat Spend ($) | B6: =SUMIF(Clean_Transactions!D:D,"Meat",Clean_Transactions!H:H) | C6: Protein / meat procurement exposure | D6: Clean_Transactions
A7: Water Spend ($) | B7: =SUM(Water_Unique!G4:G18) | C7: Validated repetitive water spend | D7: Water_Unique
A8: Unique Water Orders | B8: =COUNTA(Water_Unique!B4:B18) | C8: Deduplicated Niagara order count | D8: Water_Unique
A9: Unique Suppliers | B9: =SUMPRODUCT((Clean_Transactions!C4:C200<>"")/COUNTIF(Clean_Transactions!C4:C200,Clean_Transactions!C4:C200&"")) | C9: Supplier breadth in cleaned data | D9: Clean_Transactions
A10: Capacity Increase (Pallets) | B10: =Warehouse_Capacity!D8 | C10: Net pallet increase from redesign areas | D10: Warehouse_Capacity
A11: Capacity Increase (%) | B11: =Warehouse_Capacity!E8 | C11: Net pallet increase as % of prior capacity | D11: Warehouse_Capacity
A12: Net Usable Inbound (lbs) | B12: =Monthly_Flow!J8 | C12: Usable pounds from uploaded monthly results | D12: Monthly_Flow
A13: Estimated Water Savings @8% | B13: =B7*8% | C13: Illustrative savings if contract pricing improves | D13: Water_Unique

Sheet Controls
A1: Model Controls
A3: Input | B3: Value | C3: Explanation / Criteria
A4: Usage Weight | B4: 2 | C4: Usage Weight = 2 because demand/usage velocity is one of the strongest drivers of slotting. Fast-moving items should be easier to access to reduce travel and picking time.
A5: Flow Weight | B5: 2 | C5: Flow Weight = 2 because internal goods flow is equally critical. Items that move through inbound, staging, storage, and outbound more often should be placed to reduce congestion.
A6: Qty Received Weight | B6: 1.2 | C6: Qty Received Weight = 1.2 because large inbound batches can create staging pressure and should influence where items are slotted.
A7: Qty Held Weight | B7: 0.8 | C7: Qty Held Weight = 0.8 because on-hand stock matters, but less than usage and flow when assigning priority storage.
A8: Item Type Weight | B8: 1 | C8: Item Type Weight = 1 to reflect handling needs, such as bulk, heavy, fragile, or food-specific storage requirements.
A9: Freq Weight | B9: 1 | C9: Frequency Weight = 1 because inbound/outbound frequency helps refine movement intensity without overpowering the main usage and flow factors.
A10: A-Level Threshold | B10: 22 | C10: A-Level Threshold = 22 means only the highest-priority items qualify for premium lower/front storage locations.
A11: B-Level Threshold | B11: 16 | C11: B-Level Threshold = 16 means medium-priority items are placed in intermediate locations. Items below this generally move to C-level or deeper storage.
A12: Bulk Lower-Level Cutoff | B12: 1000 | C12: Bulk Lower-Level Cutoff = 1000 means any bulk item with more than 1,000 units held should be forced to a lower level for safety, handling, and replenishment efficiency.
A15: Cube Measurement Controls
A17: Input | B17: Value | C17: Explanation / Criteria
A18: Min Cube Height (ft) | B18: 5.25 | C18: Minimum observed cube height based on site measurement: 5'3".
A19: Max Cube Height (ft) | B19: 6.08 | C19: Maximum observed cube height based on site measurement: 6'1".
A20: Cube Width (in) | B20: 40 | C20: Observed cube width.
A21: Cube Depth (in) | B21: 48 | C21: Observed cube depth.
A22: Default Cube Height (ft) | B22: 5.67 | C22: Average working height used for volume calculations when a specific height is not assigned.
A24: Fresh Food Max Days | B24: 3 | C24: Fresh food should move within 3 days; use high flow and front-access recommendations where applicable.

Sheet Capacity_Constraints
A1: Capacity-Constrained Allocation Logic
A3: Constraint | B3: Value | C3: How Used
A4: Premium item slots | B4: 5 | C4: Only the top 5 ranked items can use premium A-level/front locations.
A5: Standard item slots | B5: 5 | C5: Next 5 ranked items are pushed to standard B-level/mid-access locations.
A6: Reserve item slots | B6: 5 | C6: Remaining items are routed to reserve/support storage.
A7: GIK role | B7: High-flow bulk zone | C7: Primary zone for water, bulk pantry, and fast protein items.
A8: FOOD role | B8: Primary food zone | C8: Main zone for staple and entrée food items.
A9: GARAGE/KITCHEN role | B9: Reserve / support zone | C9: Used for medium/low-priority reserve and support storage.
A10: ADDITIONS role | B10: Overflow bulk support | C10: Used qualitatively to support push-back overflow for very large items.
A12: Depth Optimization Rule | B12: Enabled | C12: Within each capacity bucket, items are distributed across 1 / 2 / 3 based on rank so premium items do not all go to the same front-most slot.

Sheet Field_Notes
A1: Field Notes and Operating Assumptions
A3: Note | B3: How Applied in Model
A4: Peanut butter comes in bulk around 4 times per week (1 truckload). | B4: Peanut Butter was reclassified as Bulk and its inbound/outbound frequency was increased to 4x/Week to reflect higher movement.
A5: Fresh food stays in the warehouse at most 3 days. | B5: Fresh / time-sensitive items were treated as high-flow items so they are recommended to fast-access storage.
A6: 26 pallets come to warehouse every week (not fully confirmed). | B6: This was documented as an operational note, but not used as a hard quantitative rule because it is not fully confirmed.
A7: Core slotting factors: usage rate, item type, quantity received, quantity held. | B7: These remain the core drivers in the slotting score, together with goods flow and cube-fit validation.

Sheet Storage_Reallocation_Plan
A1: Practical Storage Reallocation Plan (Score-Based Hybrid Logic)
A3: Item | B3: Current_Location | C3: Model_Ideal_Location | D3: Hybrid_Location | E3: Preferred_Area | F3: Priority_Rank | G3: Bucket | H3: Action | I3: Reason
A4: =Slotting_Model!A4 | B4: =Slotting_Model!J4 | C4: =Slotting_Model!AB4 | D4: =Slotting_Model!AO4 | E4: =Slotting_Model!AG4 | F4: =Slotting_Model!AF4 | G4: =Slotting_Model!AH4 | H4: =IF(B4=D4,"Keep in place","Move using hybrid ranking plan") | I4: =Slotting_Model!AP4
A5: =Slotting_Model!A5 | B5: =Slotting_Model!J5 | C5: =Slotting_Model!AB5 | D5: =Slotting_Model!AO5 | E5: =Slotting_Model!AG5 | F5: =Slotting_Model!AF5 | G5: =Slotting_Model!AH5 | H5: =IF(B5=D5,"Keep in place","Move using hybrid ranking plan") | I5: =Slotting_Model!AP5
A6: =Slotting_Model!A6 | B6: =Slotting_Model!J6 | C6: =Slotting_Model!AB6 | D6: =Slotting_Model!AO6 | E6: =Slotting_Model!AG6 | F6: =Slotting_Model!AF6 | G6: =Slotting_Model!AH6 | H6: =IF(B6=D6,"Keep in place","Move using hybrid ranking plan") | I6: =Slotting_Model!AP6
A7: =Slotting_Model!A7 | B7: =Slotting_Model!J7 | C7: =Slotting_Model!AB7 | D7: =Slotting_Model!AO7 | E7: =Slotting_Model!AG7 | F7: =Slotting_Model!AF7 | G7: =Slotting_Model!AH7 | H7: =IF(B7=D7,"Keep in place","Move using hybrid ranking plan") | I7: =Slotting_Model!AP7
A8: =Slotting_Model!A8 | B8: =Slotting_Model!J8 | C8: =Slotting_Model!AB8 | D8: =Slotting_Model!AO8 | E8: =Slotting_Model!AG8 | F8: =Slotting_Model!AF8 | G8: =Slotting_Model!AH8 | H8: =IF(B8=D8,"Keep in place","Move using hybrid ranking plan") | I8: =Slotting_Model!AP8
A9: =Slotting_Model!A9 | B9: =Slotting_Model!J9 | C9: =Slotting_Model!AB9 | D9: =Slotting_Model!AO9 | E9: =Slotting_Model!AG9 | F9: =Slotting_Model!AF9 | G9: =Slotting_Model!AH9 | H9: =IF(B9=D9,"Keep in place","Move using hybrid ranking plan") | I9: =Slotting_Model!AP9
A10: =Slotting_Model!A10 | B10: =Slotting_Model!J10 | C10: =Slotting_Model!AB10 | D10: =Slotting_Model!AO10 | E10: =Slotting_Model!AG10 | F10: =Slotting_Model!AF10 | G10: =Slotting_Model!AH10 | H10: =IF(B10=D10,"Keep in place","Move using hybrid ranking plan") | I10: =Slotting_Model!AP10
A11: =Slotting_Model!A11 | B11: =Slotting_Model!J11 | C11: =Slotting_Model!AB11 | D11: =Slotting_Model!AO11 | E11: =Slotting_Model!AG11 | F11: =Slotting_Model!AF11 | G11: =Slotting_Model!AH11 | H11: =IF(B11=D11,"Keep in place","Move using hybrid ranking plan") | I11: =Slotting_Model!AP11
A12: =Slotting_Model!A12 | B12: =Slotting_Model!J12 | C12: =Slotting_Model!AB12 | D12: =Slotting_Model!AO12 | E12: =Slotting_Model!AG12 | F12: =Slotting_Model!AF12 | G12: =Slotting_Model!AH12 | H12: =IF(B12=D12,"Keep in place","Move using hybrid ranking plan") | I12: =Slotting_Model!AP12
A13: =Slotting_Model!A13 | B13: =Slotting_Model!J13 | C13: =Slotting_Model!AB13 | D13: =Slotting_Model!AO13 | E13: =Slotting_Model!AG13 | F13: =Slotting_Model!AF13 | G13: =Slotting_Model!AH13 | H13: =IF(B13=D13,"Keep in place","Move using hybrid ranking plan") | I13: =Slotting_Model!AP13
A14: =Slotting_Model!A14 | B14: =Slotting_Model!J14 | C14: =Slotting_Model!AB14 | D14: =Slotting_Model!AO14 | E14: =Slotting_Model!AG14 | F14: =Slotting_Model!AF14 | G14: =Slotting_Model!AH14 | H14: =IF(B14=D14,"Keep in place","Move using hybrid ranking plan") | I14: =Slotting_Model!AP14
A15: =Slotting_Model!A15 | B15: =Slotting_Model!J15 | C15: =Slotting_Model!AB15 | D15: =Slotting_Model!AO15 | E15: =Slotting_Model!AG15 | F15: =Slotting_Model!AF15 | G15: =Slotting_Model!AH15 | H15: =IF(B15=D15,"Keep in place","Move using hybrid ranking plan") | I15: =Slotting_Model!AP15
... A18: =Slotting_Model!A18 | B18: =Slotting_Model!J18 | C18: =Slotting_Model!AB18 | D18: =Slotting_Model!AO18 | E18: =Slotting_Model!AG18 | F18: =Slotting_Model!AF18 | G18: =Slotting_Model!AH18 | H18: =IF(B18=D18,"Keep in place","Move using hybrid ranking plan") | I18: =Slotting_Model!AP18
A21: How this plan works
A22: • Premium A-level/front slots are limited to the top-ranked items only.
A23: • GIK is used for bulk/high-flow items because it has the strongest quantified expansion.
A24: • FOOD is used for core staple food items and high-use pantry items.
A25: • GARAGE/KITCHEN is used as reserve/support storage for medium and lower-priority items.
A26: • ADDITIONS is used as overflow bulk support because the drawing supports push-back expansion but does not provide a stated pallet total.

Sheet Category_Summary
A1: Category Summary
A3: Category | B3: Txn Count | C3: Net Spend ($) | D3: Spend Share | E3: Avg Ticket ($)
A4: Food | B4: =COUNTIF(Clean_Transactions!D:D,A4) | C4: =SUMIF(Clean_Transactions!D:D,A4,Clean_Transactions!H:H) | D4: =IF($C$7=0,0,C4/$C$7) | E4: =IF(B4=0,0,C4/B4)
A5: Meat | B5: =COUNTIF(Clean_Transactions!D:D,A5) | C5: =SUMIF(Clean_Transactions!D:D,A5,Clean_Transactions!H:H) | D5: =IF($C$7=0,0,C5/$C$7) | E5: =IF(B5=0,0,C5/B5)
A6: Water | B6: =COUNTIF(Clean_Transactions!D:D,A6) | C6: =SUMIF(Clean_Transactions!D:D,A6,Clean_Transactions!H:H) | D6: =IF($C$7=0,0,C6/$C$7) | E6: =IF(B6=0,0,C6/B6)
A7: Total | B7: =SUM(B4:B6) | C7: =SUM(C4:C6)

Sheet Vendor_Summary
A1: Vendor Summary
A3: Supplier | B3: Txn Count | C3: Net Spend ($) | D3: Spend Share | E3: Category Mix
A4: NIAGARA BOTTLING, LLC | B4: =COUNTIF(Clean_Transactions!C:C,A4) | C4: =SUMIF(Clean_Transactions!C:C,A4,Clean_Transactions!H:H) | D4: =IF($C$10=0,0,C4/$C$10) | E4: Water
A5: STAR FOODS INC. | B5: =COUNTIF(Clean_Transactions!C:C,A5) | C5: =SUMIF(Clean_Transactions!C:C,A5,Clean_Transactions!H:H) | D5: =IF($C$10=0,0,C5/$C$10) | E5: Food
A6: GLOBAL FOODS INC. | B6: =COUNTIF(Clean_Transactions!C:C,A6) | C6: =SUMIF(Clean_Transactions!C:C,A6,Clean_Transactions!H:H) | D6: =IF($C$10=0,0,C6/$C$10) | E6: Food, Meat
A7: CIS, LLC | B7: =COUNTIF(Clean_Transactions!C:C,A7) | C7: =SUMIF(Clean_Transactions!C:C,A7,Clean_Transactions!H:H) | D7: =IF($C$10=0,0,C7/$C$10) | E7: Food
A8: Utah Beef Producers LLC | B8: =COUNTIF(Clean_Transactions!C:C,A8) | C8: =SUMIF(Clean_Transactions!C:C,A8,Clean_Transactions!H:H) | D8: =IF($C$10=0,0,C8/$C$10) | E8: Meat
A9: Unknown | B9: =COUNTIF(Clean_Transactions!C:C,A9) | C9: =SUMIF(Clean_Transactions!C:C,A9,Clean_Transactions!H:H) | D9: =IF($C$10=0,0,C9/$C$10) | E9: Food / Water
A10: Total | B10: =SUM(B4:B9) | C10: =SUM(C4:C9)

Sheet Monthly_Flow
A1: Monthly Goods Flow
A3: Month | B3: TEFAP Lbs | C3: Regular Receipts Lbs | D3: Food Drives Lbs | E3: Truck Log Lbs | F3: Receiving Sheet Lbs | G3: RTV Lbs | H3: Garbage Out Lbs | I3: Total Inbound Lbs | J3: Net Usable Lbs
A4: Oct-2025 | B4: 1764 | C4: 89891 | D4: 0 | E4: 23795 | F4: 497495 | G4: 4728 | H4: 66380 | I4: 91655 | J4: 20547
A5: Nov-2025 | B5: 5890 | C5: 70232 | D5: 82211 | E5: 31749 | F5: 497066 | G5: 0 | H5: 43960 | I5: 158333 | J5: 114373
A6: Dec-2025 | B6: 10034 | C6: 60625 | D6: 60207 | E6: 24957 | F6: 435128 | G6: 0 | H6: 34980 | I6: 130866 | J6: 95886
A7: Jan-2026 | B7: 13180 | C7: 438120 | D7: 15600 | E7: 87625 | F7: 438120 | G7: 8178 | H7: 38600 | I7: 466900 | J7: 420122
A8: Total | B8: =SUM(B4:B7) | C8: =SUM(C4:C7) | D8: =SUM(D4:D7) | E8: =SUM(E4:E7) | F8: =SUM(F4:F7) | G8: =SUM(G4:G7) | H8: =SUM(H4:H7) | I8: =SUM(I4:I7) | J8: =SUM(J4:J7)

Sheet Warehouse_Capacity
A1: Warehouse Capacity and Layout Integration (4 Layout Files)
A3: Layout Area | B3: Before Pallets | C3: After Pallets | D3: Increase | E3: % Change | F3: How Used in Project
A4: GIK | B4: 282 | C4: 424 | D4: =C4-B4 | E4: =IF(B4=0,0,D4/B4) | F4: Used as the primary high-flow expansion zone from the GIK layout.
A5: FOOD | B5: 156 | C5: 214 | D5: =C5-B5 | E5: =IF(B5=0,0,D5/B5) | F5: Used for food storage redesign with 4-deep push-back plus selective rack.
A6: GARAGE/KITCHEN | B6: 243 | C6: 294 | D6: =C6-B6 | E6: =IF(B6=0,0,D6/B6) | F6: Combined from the Garage/Kitchen layout: garage gains capacity while kitchen trades off capacity for security and flow.
A7: ADDITIONS | F7: Used qualitatively to support the push-back expansion concept and flow logic; pallet counts were not stated on the drawing.
A8: Total Quantified | B8: =SUM(B4:B7) | C8: =SUM(C4:C7) | D8: =SUM(D4:D7) | E8: =IF(B8=0,0,D8/B8) | F8: Quantified total from GIK, FOOD, and GARAGE/KITCHEN. ADDITIONS is included as a layout input, not a quantified pallet count.

Sheet Layout_Integration
A1: Layout Integration Summary
A3: Layout File | B3: How It Was Used | C3: Quantified Impact
A4: GIK | B4: Used as the main high-flow redesign zone and capacity expansion area. | C4: +142 pallets
A5: FOOD | B5: Used for food storage redesign with push-back and selective rack. | C5: +58 pallets
A6: GARAGE/KITCHEN | B6: Used as a combined redesign source; garage gains capacity while kitchen trades off capacity for security and flow. | C6: +51 pallets net
A7: ADDITIONS | B7: Used qualitatively to support the push-back expansion concept and flow logic. | C7: Qualitative only
A10: Note | B10: The workbook now explicitly uses all 4 uploaded layouts. Quantified totals use GIK, FOOD, and GARAGE/KITCHEN because the ADDITIONS drawing did not state pallet counts.

Sheet Cube_Measurements
A1: Cube Measurements and Utilization Logic
A3: Measured Dimension | B3: Value | C3: How Used in Model
A4: Height range | B4: 5'3" to 6'1" | C4: Used to justify the average working cube height in the slotting model.
A5: Width | B5: 40" | C5: Used directly in cube volume calculation.
A6: Depth | B6: 48" | C6: Used directly in cube volume calculation.
A7: Average working height | B7: 5.67 ft | C7: Used for default cube-volume calculations across storage locations.
A8: Approx. cube volume range | B8: 69.9 to 81.0 ft³ | C8: Used to validate physical feasibility and cube utilization.
A11: Model Rule | B11: Priority-based + Fit-based | C11: Recommended storage now depends on both business priority (usage, flow, quantity) and physical fit within the cube.

Sheet Location_Map
A1: Rack Location Map (Final Corrected)
A3: Level | B3: Bay 1 | C3: Bay 2 | D3: Bay 3 | E3: Cube_Height_ft | F3: Cube_Width_in | G3: Cube_Depth_in | H3: Cube_Volume_ft3 | I3: Priority_Rule
A4: A | B4: A1-Front | C4: A2-Middle | D4: A3-Back | E4: =Controls!$B$22 | F4: =Controls!$B$20 | G4: =Controls!$B$21 | H4: =ROUND(E4*(F4/12)*(G4/12),2) | I4: High-priority / fast-access / heavier items
A5: B | B5: B1-Front | C5: B2-Middle | D5: B3-Back | E5: =Controls!$B$22 | F5: =Controls!$B$20 | G5: =Controls!$B$21 | H5: =ROUND(E5*(F5/12)*(G5/12),2) | I5: Medium-priority items
A6: C | B6: C1-Front | C6: C2-Middle | D6: C3-Back | E6: =Controls!$B$22 | F6: =Controls!$B$20 | G6: =Controls!$B$21 | H6: =ROUND(E6*(F6/12)*(G6/12),2) | I6: Low-priority / reserve / overflow
A8: Location Logic
A9: A-level = High-priority / fast-access / heavier items
A10: B-level = Medium-priority / standard access
A11: C-level = Low-priority / reserve / overflow
A12: Front = fastest access, Middle = balanced access, Back = reserve / deeper storage

Sheet Lookup_Tables
A1: Lookup Tables | G1: Item Type Volume Assumptions | L1: Preferred Area Map
A3: Item Type | B3: Weight | D3: Frequency | E3: Score | G3: Item_Type | H3: Required_Volume_ft3 | I3: Fit Rule | J3: Rationale | L3: Item | M3: Preferred_Area | N3: Why
A4: Bulk | B4: 5 | D4: Daily | E4: 5 | G4: Bulk | H4: 72 | I4: Needs lower level if held qty is high | J4: Bulk items like water use more cube space and are heavier. | L4: Water | M4: GIK | N4: High-volume bulk, strong fit for lower-level high-flow expansion zone.
A5: Food | B5: 4 | D5: Weekly | E5: 4 | G5: Food | H5: 35 | I5: Standard cube fit | J5: Most dry/canned food items fit within a standard cube. | L5: Peanut Butter | M5: GIK | N5: Bulk-like pantry staple with high inbound frequency.
A6: Meat | B6: 4 | D6: Biweekly | E6: 3 | G6: Meat | H6: 48 | I6: Cold-chain / handling sensitive | J6: Protein/meat items need more buffer and handling allowance. | L6: Chicken Leg Quarters | M6: GIK | N6: High-flow protein item needing fast access.
A7: Fragile | B7: 3 | D7: 4x/Week | E7: 4.5 | G7: Fragile | H7: 28 | I7: Avoid deep/back where possible | J7: Fragile items should not be forced into tight/deep locations. | L7: Ground Beef | M7: ADDITIONS | N7: Very high volume; use overflow push-back concept supported by additions layout.
A8: Other | B8: 3 | D8: Biweekly | E8: 3 | L8: Tuna | M8: FOOD | N8: Fast-moving food staple; should stay in primary food zone.
D9: Weekly | E9: 4 | L9: Rice | M9: FOOD | N9: Core staple suited to food zone.
D10: Monthly | E10: 2 | L10: Black Beans | M10: FOOD | N10: Core staple suited to food zone.
D11: Ad Hoc | E11: 1 | L11: Pasta Sauce | M11: FOOD | N11: Food zone standard-access item.
L12: Oats | M12: GARAGE/KITCHEN | N12: Medium-priority food; can use reserve/support storage.
L13: Pancake Mix | M13: GARAGE/KITCHEN | N13: Medium-priority food; can use support storage.
L14: Peaches | M14: GARAGE/KITCHEN | N14: Lower-priority reserve/support placement.
L15: Chili - Beef | M15: FOOD | N15: High-demand food entrée item.
L16: Mixed Vegetables | M16: GARAGE/KITCHEN | N16: Reserve/support storage is acceptable.
L17: Green Beans | M17: FOOD | N17: Food zone staple item.
L18: Macaroni in Tomato Sauce | M18: FOOD | N18: High-usage entrée item in primary food area.

Sheet Slotting_Model
A1: Slotting Model (Hybrid Logic Applied)
A2: Hybrid ranking order used in this workbook: A1 → B1 → C1 → A2 → B2 → A3 → B3 → C2 → C3
A3: Item | B3: Category | C3: Item_Type | D3: Usage_Rate | E3: Qty_Received | F3: Qty_Held | G3: Flow_Priority | H3: Inbound_Freq | I3: Outbound_Freq | J3: Current_Location | K3: Cube_Height_ft | L3: Cube_Width_in | M3: Cube_Depth_in | N3: Cube_Volume_ft3 | O3: Item_Required_Volume_ft3 | P3: Fit_Check | Q3: Cube_Utilization_% | R3: Prelim_Recommendation | S3: Qty_Received_Score | T3: Qty_Held_Score | U3: ItemType_Weight | V3: Inbound_Score | W3: Outbound_Score | X3: Storage_Priority_Score | Y3: Recommended_Level | Z3: Recommended_Bay | AA3: Recommended_Depth | AB3: Final_Recommended_Location | AC3: Reason | AD3: Bulk_Flag | AE3: Model_Note | AF3: Priority_Rank | AG3: Preferred_Area | AH3: Capacity_Bucket | AI3: Capacity_Constrained_Location | AJ3: Implementation_Action | AK3: Bucket_Rank_By_Score | AL3: Depth_Optimized_Location | AM3: Depth_Optimization_Note | AN3: Hybrid_Order_Index | AO3: Hybrid_Location | AP3: Hybrid_Reason
A4: Water | B4: Water | C4: Bulk | D4: 5 | E4: 960 | F4: 1500 | G4: 5 | H4: Weekly | I4: Daily | J4: B2-Back | K4: =Controls!$B$22 | L4: =Controls!$B$20 | M4: =Controls!$B$21 | N4: =ROUND(K4*(L4/12)*(M4/12),2) | O4: =IFERROR(VLOOKUP(C4,Lookup_Tables!$G$4:$H$7,2,FALSE),35) | P4: =IF(O4<=N4,"Fits","Review") | Q4: =ROUND(O4/N4,3) | R4: =Y4&Z4&"-"&AA4 | S4: =IF(E4>=1000,5,IF(E4>=500,4,IF(E4>=250,3,IF(E4>=100,2,1)))) | T4: =IF(F4>=1000,5,IF(F4>=500,4,IF(F4>=250,3,IF(F4>=100,2,1)))) | U4: =IFERROR(VLOOKUP(C4,Lookup_Tables!$A$4:$B$8,2,FALSE),3) | V4: =IFERROR(VLOOKUP(H4,Lookup_Tables!$D$4:$E$11,2,FALSE),2) | W4: =IFERROR(VLOOKUP(I4,Lookup_Tables!$D$4:$E$11,2,FALSE),2) | X4: =ROUND((D4*Controls!$B$4)+(G4*Controls!$B$5)+(S4*Controls!$B$6)+(T4*Controls!$B$7)+(U4*Controls!$B$8)+(MAX(V4,W4)*Controls!$B$9),2) | Y4: =IF(AD4="Bulk","A",IF(X4>=Controls!$B$10,"A",IF(X4>=Controls!$B$11,"B","C"))) | Z4: =IF(OR(D4>=4,G4>=4),1,IF(X4>=Controls!$B$11,2,3)) | AA4: =IF(OR(D4>=4,G4>=4),"Front",IF(X4>=Controls!$B$11,"Middle","Back")) | AB4: =IF(P4="Fits",R4,"Manual Review") | AC4: =IF(AD4="Bulk","Bulk / heavy item -> lower level priority",IF(P4<>"Fits","Review cube fit before assigning location",IF(AND(D4>=4,G4>=4),"High usage + high flow -> front-access priority",IF(X4>=Controls!$B$11,"Medium priority item -> standard access","Low priority / reserve storage")))) | AD4: =IF(OR(C4="Bulk",F4>=Controls!$B$12),"Bulk","Non-Bulk") | AE4: High-volume bulk item; lower-level fast-access rule applies. | AF4: =RANK(X4,$X$4:$X$18,0)+COUNTIF($X$4:X4,X4)-1 | AG4: =IFERROR(VLOOKUP(A4,Lookup_Tables!$L$4:$M$18,2,FALSE),"FOOD") | AH4: =IF(AF4<=5,"Premium",IF(AF4<=11,"Standard","Reserve")) | AI4: =IF(AH4="Premium",IF(AG4="GIK","GIK-A"&MOD(AF4-1,3)+1&"-Front",IF(AG4="FOOD","FOOD-A"&MOD(AF4-1,3)+1&"-Front",IF(AG4="ADDITIONS","ADD-A"&MOD(AF4-1,2)+1&"-Front","GAR-A"&MOD(AF4-1,2)+1&"-Front"))),IF(AH4="Standard",IF(AG4="GIK","GIK-B"&MOD(AF4-1,3)+1&"-Middle",IF(AG4="FOOD","FOOD-B"&MOD(AF4-1,3)+1&"-Middle",IF(AG4="ADDITIONS","ADD-B"&MOD(AF4-1,2)+1&"-Middle","GAR-B"&MOD(AF4-1,2)+1&"-Middle"))),IF(AG4="GIK","GIK-C"&MOD(AF4-1,3)+1&"-Back",IF(AG4="FOOD","FOOD-C"&MOD(AF4-1,3)+1&"-Back",IF(AG4="ADDITIONS","ADD-C"&MOD(AF4-1,2)+1&"-Back","GAR-C"&MOD(AF4-1,2)+1&"-Back"))))) | AJ4: =IF(J4=AI4,"Keep in place",IF(LEFT(J4,3)=LEFT(AI4,3),"Re-slot within same zone","Move to "&AG4&" based on flow, capacity, and layout logic")) | AK4: =IF(AH4="Premium",AF4,IF(AH4="Standard",AF4-5,AF4-11)) | AL4: =IF(AH4="Premium",AG4&"-A"&MOD(AK4-1,3)+1&"-Front",IF(AH4="Standard",AG4&"-B"&MOD(AK4-1,3)+1&"-Middle",AG4&"-C"&MOD(AK4-1,3)+1&"-Back")) | AM4: =IF(AH4="Premium","Premium item distributed across A1/A2/A3 by rank to avoid overloading one slot",IF(AH4="Standard","Standard item distributed across B1/B2/B3 by rank","Reserve item distributed across C1/C2/C3 by rank")) | AN4: =MOD(AK4-1,9)+1 | AO4: =IF(AN4=1,AG4&"-A1-Front",IF(AN4=2,AG4&"-B1-Front",IF(AN4=3,AG4&"-C1-Front",IF(AN4=4,AG4&"-A2-Middle",IF(AN4=5,AG4&"-B2-Middle",IF(AN4=6,AG4&"-A3-Back",IF(AN4=7,AG4&"-B3-Back",IF(AN4=8,AG4&"-C2-Middle",AG4&"-C3-Back")))))))) | AP4: =IF(AH4="Premium","Premium item positioned by score rank within premium bucket",IF(AH4="Standard","Standard item positioned by score rank within standard bucket","Reserve item positioned by score rank within reserve bucket"))
A5: Tuna | B5: Food | C5: Food | D5: 5 | E5: 126 | F5: 250 | G5: 5 | H5: Weekly | I5: Daily | J5: B1-Middle | K5: =Controls!$B$22 | L5: =Controls!$B$20 | M5: =Controls!$B$21 | N5: =ROUND(K5*(L5/12)*(M5/12),2) | O5: =IFERROR(VLOOKUP(C5,Lookup_Tables!$G$4:$H$7,2,FALSE),35) | P5: =IF(O5<=N5,"Fits","Review") | Q5: =ROUND(O5/N5,3) | R5: =Y5&Z5&"-"&AA5 | S5: =IF(E5>=1000,5,IF(E5>=500,4,IF(E5>=250,3,IF(E5>=100,2,1)))) | T5: =IF(F5>=1000,5,IF(F5>=500,4,IF(F5>=250,3,IF(F5>=100,2,1)))) | U5: =IFERROR(VLOOKUP(C5,Lookup_Tables!$A$4:$B$8,2,FALSE),3) | V5: =IFERROR(VLOOKUP(H5,Lookup_Tables!$D$4:$E$11,2,FALSE),2) | W5: =IFERROR(VLOOKUP(I5,Lookup_Tables!$D$4:$E$11,2,FALSE),2) | X5: =ROUND((D5*Controls!$B$4)+(G5*Controls!$B$5)+(S5*Controls!$B$6)+(T5*Controls!$B$7)+(U5*Controls!$B$8)+(MAX(V5,W5)*Controls!$B$9),2) | Y5: =IF(AD5="Bulk","A",IF(X5>=Controls!$B$10,"A",IF(X5>=Controls!$B$11,"B","C"))) | Z5: =IF(OR(D5>=4,G5>=4),1,IF(X5>=Controls!$B$11,2,3)) | AA5: =IF(OR(D5>=4,G5>=4),"Front",IF(X5>=Controls!$B$11,"Middle","Back")) | AB5: =IF(P5="Fits",R5,"Manual Review") | AC5: =IF(AD5="Bulk","Bulk / heavy item -> lower level priority",IF(P5<>"Fits","Review cube fit before assigning location",IF(AND(D5>=4,G5>=4),"High usage + high flow -> front-access priority",IF(X5>=Controls!$B$11,"Medium priority item -> standard access","Low priority / reserve storage")))) | AD5: =IF(OR(C5="Bulk",F5>=Controls!$B$12),"Bulk","Non-Bulk") | AF5: =RANK(X5,$X$4:$X$18,0)+COUNTIF($X$4:X5,X5)-1 | AG5: =IFERROR(VLOOKUP(A5,Lookup_Tables!$L$4:$M$18,2,FALSE),"FOOD") | AH5: =IF(AF5<=5,"Premium",IF(AF5<=11,"Standard","Reserve")) | AI5: =IF(AH5="Premium",IF(AG5="GIK","GIK-A"&MOD(AF5-1,3)+1&"-Front",IF(AG5="FOOD","FOOD-A"&MOD(AF5-1,3)+1&"-Front",IF(AG5="ADDITIONS","ADD-A"&MOD(AF5-1,2)+1&"-Front","GAR-A"&MOD(AF5-1,2)+1&"-Front"))),IF(AH5="Standard",IF(AG5="GIK","GIK-B"&MOD(AF5-1,3)+1&"-Middle",IF(AG5="FOOD","FOOD-B"&MOD(AF5-1,3)+1&"-Middle",IF(AG5="ADDITIONS","ADD-B"&MOD(AF5-1,2)+1&"-Middle","GAR-B"&MOD(AF5-1,2)+1&"-Middle"))),IF(AG5="GIK","GIK-C"&MOD(AF5-1,3)+1&"-Back",IF(AG5="FOOD","FOOD-C"&MOD(AF5-1,3)+1&"-Back",IF(AG5="ADDITIONS","ADD-C"&MOD(AF5-1,2)+1&"-Back","GAR-C"&MOD(AF5-1,2)+1&"-Back"))))) | AJ5: =IF(J5=AI5,"Keep in place",IF(LEFT(J5,3)=LEFT(AI5,3),"Re-slot within same zone","Move to "&AG5&" based on flow, capacity, and layout logic")) | AK5: =IF(AH5="Premium",AF5,IF(AH5="Standard",AF5-5,AF5-11)) | AL5: =IF(AH5="Premium",AG5&"-A"&MOD(AK5-1,3)+1&"-Front",IF(AH5="Standard",AG5&"-B"&MOD(AK5-1,3)+1&"-Middle",AG5&"-C"&MOD(AK5-1,3)+1&"-Back")) | AM5: =IF(AH5="Premium","Premium item distributed across A1/A2/A3 by rank to avoid overloading one slot",IF(AH5="Standard","Standard item distributed across B1/B2/B3 by rank","Reserve item distributed across C1/C2/C3 by rank")) | AN5: =MOD(AK5-1,9)+1 | AO5: =IF(AN5=1,AG5&"-A1-Front",IF(AN5=2,AG5&"-B1-Front",IF(AN5=3,AG5&"-C1-Front",IF(AN5=4,AG5&"-A2-Middle",IF(AN5=5,AG5&"-B2-Middle",IF(AN5=6,AG5&"-A3-Back",IF(AN5=7,AG5&"-B3-Back",IF(AN5=8,AG5&"-C2-Middle",AG5&"-C3-Back")))))))) | AP5: =IF(AH5="Premium","Premium item positioned by score rank within premium bucket",IF(AH5="Standard","Standard item positioned by score rank within standard bucket","Reserve item positioned by score rank within reserve bucket"))
A6: Rice | B6: Food | C6: Food | D6: 4 | E6: 115 | F6: 300 | G6: 4 | H6: Weekly | I6: Daily | J6: B2-Middle | K6: =Controls!$B$22 | L6: =Controls!$B$20 | M6: =Controls!$B$21 | N6: =ROUND(K6*(L6/12)*(M6/12),2) | O6: =IFERROR(VLOOKUP(C6,Lookup_Tables!$G$4:$H$7,2,FALSE),35) | P6: =IF(O6<=N6,"Fits","Review") | Q6: =ROUND(O6/N6,3) | R6: =Y6&Z6&"-"&AA6 | S6: =IF(E6>=1000,5,IF(E6>=500,4,IF(E6>=250,3,IF(E6>=100,2,1)))) | T6: =IF(F6>=1000,5,IF(F6>=500,4,IF(F6>=250,3,IF(F6>=100,2,1)))) | U6: =IFERROR(VLOOKUP(C6,Lookup_Tables!$A$4:$B$8,2,FALSE),3) | V6: =IFERROR(VLOOKUP(H6,Lookup_Tables!$D$4:$E$11,2,FALSE),2) | W6: =IFERROR(VLOOKUP(I6,Lookup_Tables!$D$4:$E$11,2,FALSE),2) | X6: =ROUND((D6*Controls!$B$4)+(G6*Controls!$B$5)+(S6*Controls!$B$6)+(T6*Controls!$B$7)+(U6*Controls!$B$8)+(MAX(V6,W6)*Controls!$B$9),2) | Y6: =IF(AD6="Bulk","A",IF(X6>=Controls!$B$10,"A",IF(X6>=Controls!$B$11,"B","C"))) | Z6: =IF(OR(D6>=4,G6>=4),1,IF(X6>=Controls!$B$11,2,3)) | AA6: =IF(OR(D6>=4,G6>=4),"Front",IF(X6>=Controls!$B$11,"Middle","Back")) | AB6: =IF(P6="Fits",R6,"Manual Review") | AC6: =IF(AD6="Bulk","Bulk / heavy item -> lower level priority",IF(P6<>"Fits","Review cube fit before assigning location",IF(AND(D6>=4,G6>=4),"High usage + high flow -> front-access priority",IF(X6>=Controls!$B$11,"Medium priority item -> standard access","Low priority / reserve storage")))) | AD6: =IF(OR(C6="Bulk",F6>=Controls!$B$12),"Bulk","Non-Bulk") | AF6: =RANK(X6,$X$4:$X$18,0)+COUNTIF($X$4:X6,X6)-1 | AG6: =IFERROR(VLOOKUP(A6,Lookup_Tables!$L$4:$M$18,2,FALSE),"FOOD") | AH6: =IF(AF6<=5,"Premium",IF(AF6<=11,"Standard","Reserve")) | AI6: =IF(AH6="Premium",IF(AG6="GIK","GIK-A"&MOD(AF6-1,3)+1&"-Front",IF(AG6="FOOD","FOOD-A"&MOD(AF6-1,3)+1&"-Front",IF(AG6="ADDITIONS","ADD-A"&MOD(AF6-1,2)+1&"-Front","GAR-A"&MOD(AF6-1,2)+1&"-Front"))),IF(AH6="Standard",IF(AG6="GIK","GIK-B"&MOD(AF6-1,3)+1&"-Middle",IF(AG6="FOOD","FOOD-B"&MOD(AF6-1,3)+1&"-Middle",IF(AG6="ADDITIONS","ADD-B"&MOD(AF6-1,2)+1&"-Middle","GAR-B"&MOD(AF6-1,2)+1&"-Middle"))),IF(AG6="GIK","GIK-C"&MOD(AF6-1,3)+1&"-Back",IF(AG6="FOOD","FOOD-C"&MOD(AF6-1,3)+1&"-Back",IF(AG6="ADDITIONS","ADD-C"&MOD(AF6-1,2)+1&"-Back","GAR-C"&MOD(AF6-1,2)+1&"-Back"))))) | AJ6: =IF(J6=AI6,"Keep in place",IF(LEFT(J6,3)=LEFT(AI6,3),"Re-slot within same zone","Move to "&AG6&" based on flow, capacity, and layout logic")) | AK6: =IF(AH6="Premium",AF6,IF(AH6="Standard",AF6-5,AF6-11)) | AL6: =IF(AH6="Premium",AG6&"-A"&MOD(AK6-1,3)+1&"-Front",IF(AH6="Standard",AG6&"-B"&MOD(AK6-1,3)+1&"-Middle",AG6&"-C"&MOD(AK6-1,3)+1&"-Back")) | AM6: =IF(AH6="Premium","Premium item distributed across A1/A2/A3 by rank to avoid overloading one slot",IF(AH6="Standard","Standard item distributed across B1/B2/B3 by rank","Reserve item distributed across C1/C2/C3 by rank")) | AN6: =MOD(AK6-1,9)+1 | AO6: =IF(AN6=1,AG6&"-A1-Front",IF(AN6=2,AG6&"-B1-Front",IF(AN6=3,AG6&"-C1-Front",IF(AN6=4,AG6&"-A2-Middle",IF(AN6=5,AG6&"-B2-Middle",IF(AN6=6,AG6&"-A3-Back",IF(AN6=7,AG6&"-B3-Back",IF(AN6=8,AG6&"-C2-Middle",AG6&"-C3-Back")))))))) | AP6: =IF(AH6="Premium","Premium item positioned by score rank within premium bucket",IF(AH6="Standard","Standard item positioned by score rank within standard bucket","Reserve item positioned by score rank within reserve bucket"))
A7: Black Beans | B7: Food | C7: Food | D7: 4 | E7: 96 | F7: 280 | G7: 4 | H7: Weekly | I7: Daily | J7: B3-Middle | K7: =Controls!$B$22 | L7: =Controls!$B$20 | M7: =Controls!$B$21 | N7: =ROUND(K7*(L7/12)*(M7/12),2) | O7: =IFERROR(VLOOKUP(C7,Lookup_Tables!$G$4:$H$7,2,FALSE),35) | P7: =IF(O7<=N7,"Fits","Review") | Q7: =ROUND(O7/N7,3) | R7: =Y7&Z7&"-"&AA7 | S7: =IF(E7>=1000,5,IF(E7>=500,4,IF(E7>=250,3,IF(E7>=100,2,1)))) | T7: =IF(F7>=1000,5,IF(F7>=500,4,IF(F7>=250,3,IF(F7>=100,2,1)))) | U7: =IFERROR(VLOOKUP(C7,Lookup_Tables!$A$4:$B$8,2,FALSE),3) | V7: =IFERROR(VLOOKUP(H7,Lookup_Tables!$D$4:$E$11,2,FALSE),2) | W7: =IFERROR(VLOOKUP(I7,Lookup_Tables!$D$4:$E$11,2,FALSE),2) | X7: =ROUND((D7*Controls!$B$4)+(G7*Controls!$B$5)+(S7*Controls!$B$6)+(T7*Controls!$B$7)+(U7*Controls!$B$8)+(MAX(V7,W7)*Controls!$B$9),2) | Y7: =IF(AD7="Bulk","A",IF(X7>=Controls!$B$10,"A",IF(X7>=Controls!$B$11,"B","C"))) | Z7: =IF(OR(D7>=4,G7>=4),1,IF(X7>=Controls!$B$11,2,3)) | AA7: =IF(OR(D7>=4,G7>=4),"Front",IF(X7>=Controls!$B$11,"Middle","Back")) | AB7: =IF(P7="Fits",R7,"Manual Review") | AC7: =IF(AD7="Bulk","Bulk / heavy item -> lower level priority",IF(P7<>"Fits","Review cube fit before assigning location",IF(AND(D7>=4,G7>=4),"High usage + high flow -> front-access priority",IF(X7>=Controls!$B$11,"Medium priority item -> standard access","Low priority / reserve storage")))) | AD7: =IF(OR(C7="Bulk",F7>=Controls!$B$12),"Bulk","Non-Bulk") | AF7: =RANK(X7,$X$4:$X$18,0)+COUNTIF($X$4:X7,X7)-1 | AG7: =IFERROR(VLOOKUP(A7,Lookup_Tables!$L$4:$M$18,2,FALSE),"FOOD") | AH7: =IF(AF7<=5,"Premium",IF(AF7<=11,"Standard","Reserve")) | AI7: =IF(AH7="Premium",IF(AG7="GIK","GIK-A"&MOD(AF7-1,3)+1&"-Front",IF(AG7="FOOD","FOOD-A"&MOD(AF7-1,3)+1&"-Front",IF(AG7="ADDITIONS","ADD-A"&MOD(AF7-1,2)+1&"-Front","GAR-A"&MOD(AF7-1,2)+1&"-Front"))),IF(AH7="Standard",IF(AG7="GIK","GIK-B"&MOD(AF7-1,3)+1&"-Middle",IF(AG7="FOOD","FOOD-B"&MOD(AF7-1,3)+1&"-Middle",IF(AG7="ADDITIONS","ADD-B"&MOD(AF7-1,2)+1&"-Middle","GAR-B"&MOD(AF7-1,2)+1&"-Middle"))),IF(AG7="GIK","GIK-C"&MOD(AF7-1,3)+1&"-Back",IF(AG7="FOOD","FOOD-C"&MOD(AF7-1,3)+1&"-Back",IF(AG7="ADDITIONS","ADD-C"&MOD(AF7-1,2)+1&"-Back","GAR-C"&MOD(AF7-1,2)+1&"-Back"))))) | AJ7: =IF(J7=AI7,"Keep in place",IF(LEFT(J7,3)=LEFT(AI7,3),"Re-slot within same zone","Move to "&AG7&" based on flow, capacity, and layout logic")) | AK7: =IF(AH7="Premium",AF7,IF(AH7="Standard",AF7-5,AF7-11)) | AL7: =IF(AH7="Premium",AG7&"-A"&MOD(AK7-1,3)+1&"-Front",IF(AH7="Standard",AG7&"-B"&MOD(AK7-1,3)+1&"-Middle",AG7&"-C"&MOD(AK7-1,3)+1&"-Back")) | AM7: =IF(AH7="Premium","Premium item distributed across A1/A2/A3 by rank to avoid overloading one slot",IF(AH7="Standard","Standard item distributed across B1/B2/B3 by rank","Reserve item distributed across C1/C2/C3 by rank")) | AN7: =MOD(AK7-1,9)+1 | AO7: =IF(AN7=1,AG7&"-A1-Front",IF(AN7=2,AG7&"-B1-Front",IF(AN7=3,AG7&"-C1-Front",IF(AN7=4,AG7&"-A2-Middle",IF(AN7=5,AG7&"-B2-Middle",IF(AN7=6,AG7&"-A3-Back",IF(AN7=7,AG7&"-B3-Back",IF(AN7=8,AG7&"-C2-Middle",AG7&"-C3-Back")))))))) | AP7: =IF(AH7="Premium","Premium item positioned by score rank within premium bucket",IF(AH7="Standard","Standard item positioned by score rank within standard bucket","Reserve item positioned by score rank within reserve bucket"))
A8: Peanut Butter | B8: Food | C8: Bulk | D8: 5 | E8: 135 | F8: 220 | G8: 5 | H8: 4x/Week | I8: 4x/Week | J8: B2-Front | K8: =Controls!$B$22 | L8: =Controls!$B$20 | M8: =Controls!$B$21 | N8: =ROUND(K8*(L8/12)*(M8/12),2) | O8: =IFERROR(VLOOKUP(C8,Lookup_Tables!$G$4:$H$7,2,FALSE),35) | P8: =IF(O8<=N8,"Fits","Review") | Q8: =ROUND(O8/N8,3) | R8: =Y8&Z8&"-"&AA8 | S8: =IF(E8>=1000,5,IF(E8>=500,4,IF(E8>=250,3,IF(E8>=100,2,1)))) | T8: =IF(F8>=1000,5,IF(F8>=500,4,IF(F8>=250,3,IF(F8>=100,2,1)))) | U8: =IFERROR(VLOOKUP(C8,Lookup_Tables!$A$4:$B$8,2,FALSE),3) | V8: =IFERROR(VLOOKUP(H8,Lookup_Tables!$D$4:$E$11,2,FALSE),2) | W8: =IFERROR(VLOOKUP(I8,Lookup_Tables!$D$4:$E$11,2,FALSE),2) | X8: =ROUND((D8*Controls!$B$4)+(G8*Controls!$B$5)+(S8*Controls!$B$6)+(T8*Controls!$B$7)+(U8*Controls!$B$8)+(MAX(V8,W8)*Controls!$B$9),2) | Y8: =IF(AD8="Bulk","A",IF(X8>=Controls!$B$10,"A",IF(X8>=Controls!$B$11,"B","C"))) | Z8: =IF(OR(D8>=4,G8>=4),1,IF(X8>=Controls!$B$11,2,3)) | AA8: =IF(OR(D8>=4,G8>=4),"Front",IF(X8>=Controls!$B$11,"Middle","Back")) | AB8: =IF(P8="Fits",R8,"Manual Review") | AC8: =IF(AD8="Bulk","Bulk / heavy item -> lower level priority",IF(P8<>"Fits","Review cube fit before assigning location",IF(AND(D8>=4,G8>=4),"High usage + high flow -> front-access priority",IF(X8>=Controls!$B$11,"Medium priority item -> standard access","Low priority / reserve storage")))) | AD8: =IF(OR(C8="Bulk",F8>=Controls!$B$12),"Bulk","Non-Bulk") | AE8: Updated from field note: peanut butter arrives in bulk about 4 times per week. | AF8: =RANK(X8,$X$4:$X$18,0)+COUNTIF($X$4:X8,X8)-1 | AG8: =IFERROR(VLOOKUP(A8,Lookup_Tables!$L$4:$M$18,2,FALSE),"FOOD") | AH8: =IF(AF8<=5,"Premium",IF(AF8<=11,"Standard","Reserve")) | AI8: =IF(AH8="Premium",IF(AG8="GIK","GIK-A"&MOD(AF8-1,3)+1&"-Front",IF(AG8="FOOD","FOOD-A"&MOD(AF8-1,3)+1&"-Front",IF(AG8="ADDITIONS","ADD-A"&MOD(AF8-1,2)+1&"-Front","GAR-A"&MOD(AF8-1,2)+1&"-Front"))),IF(AH8="Standard",IF(AG8="GIK","GIK-B"&MOD(AF8-1,3)+1&"-Middle",IF(AG8="FOOD","FOOD-B"&MOD(AF8-1,3)+1&"-Middle",IF(AG8="ADDITIONS","ADD-B"&MOD(AF8-1,2)+1&"-Middle","GAR-B"&MOD(AF8-1,2)+1&"-Middle"))),IF(AG8="GIK","GIK-C"&MOD(AF8-1,3)+1&"-Back",IF(AG8="FOOD","FOOD-C"&MOD(AF8-1,3)+1&"-Back",IF(AG8="ADDITIONS","ADD-C"&MOD(AF8-1,2)+1&"-Back","GAR-C"&MOD(AF8-1,2)+1&"-Back"))))) | AJ8: =IF(J8=AI8,"Keep in place",IF(LEFT(J8,3)=LEFT(AI8,3),"Re-slot within same zone","Move to "&AG8&" based on flow, capacity, and layout logic")) | AK8: =IF(AH8="Premium",AF8,IF(AH8="Standard",AF8-5,AF8-11)) | AL8: =IF(AH8="Premium",AG8&"-A"&MOD(AK8-1,3)+1&"-Front",IF(AH8="Standard",AG8&"-B"&MOD(AK8-1,3)+1&"-Middle",AG8&"-C"&MOD(AK8-1,3)+1&"-Back")) | AM8: =IF(AH8="Premium","Premium item distributed across A1/A2/A3 by rank to avoid overloading one slot",IF(AH8="Standard","Standard item distributed across B1/B2/B3 by rank","Reserve item distributed across C1/C2/C3 by rank")) | AN8: =MOD(AK8-1,9)+1 | AO8: =IF(AN8=1,AG8&"-A1-Front",IF(AN8=2,AG8&"-B1-Front",IF(AN8=3,AG8&"-C1-Front",IF(AN8=4,AG8&"-A2-Middle",IF(AN8=5,AG8&"-B2-Middle",IF(AN8=6,AG8&"-A3-Back",IF(AN8=7,AG8&"-B3-Back",IF(AN8=8,AG8&"-C2-Middle",AG8&"-C3-Back")))))))) | AP8: =IF(AH8="Premium","Premium item positioned by score rank within premium bucket",IF(AH8="Standard","Standard item positioned by score rank within standard bucket","Reserve item positioned by score rank within reserve bucket"))
A9: Pasta Sauce | B9: Food | C9: Food | D9: 3 | E9: 96 | F9: 180 | G9: 3 | H9: Weekly | I9: Weekly | J9: C1-Middle | K9: =Controls!$B$22 | L9: =Controls!$B$20 | M9: =Controls!$B$21 | N9: =ROUND(K9*(L9/12)*(M9/12),2) | O9: =IFERROR(VLOOKUP(C9,Lookup_Tables!$G$4:$H$7,2,FALSE),35) | P9: =IF(O9<=N9,"Fits","Review") | Q9: =ROUND(O9/N9,3) | R9: =Y9&Z9&"-"&AA9 | S9: =IF(E9>=1000,5,IF(E9>=500,4,IF(E9>=250,3,IF(E9>=100,2,1)))) | T9: =IF(F9>=1000,5,IF(F9>=500,4,IF(F9>=250,3,IF(F9>=100,2,1)))) | U9: =IFERROR(VLOOKUP(C9,Lookup_Tables!$A$4:$B$8,2,FALSE),3) | V9: =IFERROR(VLOOKUP(H9,Lookup_Tables!$D$4:$E$11,2,FALSE),2) | W9: =IFERROR(VLOOKUP(I9,Lookup_Tables!$D$4:$E$11,2,FALSE),2) | X9: =ROUND((D9*Controls!$B$4)+(G9*Controls!$B$5)+(S9*Controls!$B$6)+(T9*Controls!$B$7)+(U9*Controls!$B$8)+(MAX(V9,W9)*Controls!$B$9),2) | Y9: =IF(AD9="Bulk","A",IF(X9>=Controls!$B$10,"A",IF(X9>=Controls!$B$11,"B","C"))) | Z9: =IF(OR(D9>=4,G9>=4),1,IF(X9>=Controls!$B$11,2,3)) | AA9: =IF(OR(D9>=4,G9>=4),"Front",IF(X9>=Controls!$B$11,"Middle","Back")) | AB9: =IF(P9="Fits",R9,"Manual Review") | AC9: =IF(AD9="Bulk","Bulk / heavy item -> lower level priority",IF(P9<>"Fits","Review cube fit before assigning location",IF(AND(D9>=4,G9>=4),"High usage + high flow -> front-access priority",IF(X9>=Controls!$B$11,"Medium priority item -> standard access","Low priority / reserve storage")))) | AD9: =IF(OR(C9="Bulk",F9>=Controls!$B$12),"Bulk","Non-Bulk") | AF9: =RANK(X9,$X$4:$X$18,0)+COUNTIF($X$4:X9,X9)-1 | AG9: =IFERROR(VLOOKUP(A9,Lookup_Tables!$L$4:$M$18,2,FALSE),"FOOD") | AH9: =IF(AF9<=5,"Premium",IF(AF9<=11,"Standard","Reserve")) | AI9: =IF(AH9="Premium",IF(AG9="GIK","GIK-A"&MOD(AF9-1,3)+1&"-Front",IF(AG9="FOOD","FOOD-A"&MOD(AF9-1,3)+1&"-Front",IF(AG9="ADDITIONS","ADD-A"&MOD(AF9-1,2)+1&"-Front","GAR-A"&MOD(AF9-1,2)+1&"-Front"))),IF(AH9="Standard",IF(AG9="GIK","GIK-B"&MOD(AF9-1,3)+1&"-Middle",IF(AG9="FOOD","FOOD-B"&MOD(AF9-1,3)+1&"-Middle",IF(AG9="ADDITIONS","ADD-B"&MOD(AF9-1,2)+1&"-Middle","GAR-B"&MOD(AF9-1,2)+1&"-Middle"))),IF(AG9="GIK","GIK-C"&MOD(AF9-1,3)+1&"-Back",IF(AG9="FOOD","FOOD-C"&MOD(AF9-1,3)+1&"-Back",IF(AG9="ADDITIONS","ADD-C"&MOD(AF9-1,2)+1&"-Back","GAR-C"&MOD(AF9-1,2)+1&"-Back"))))) | AJ9: =IF(J9=AI9,"Keep in place",IF(LEFT(J9,3)=LEFT(AI9,3),"Re-slot within same zone","Move to "&AG9&" based on flow, capacity, and layout logic")) | AK9: =IF(AH9="Premium",AF9,IF(AH9="Standard",AF9-5,AF9-11)) | AL9: =IF(AH9="Premium",AG9&"-A"&MOD(AK9-1,3)+1&"-Front",IF(AH9="Standard",AG9&"-B"&MOD(AK9-1,3)+1&"-Middle",AG9&"-C"&MOD(AK9-1,3)+1&"-Back")) | AM9: =IF(AH9="Premium","Premium item distributed across A1/A2/A3 by rank to avoid overloading one slot",IF(AH9="Standard","Standard item distributed across B1/B2/B3 by rank","Reserve item distributed across C1/C2/C3 by rank")) | AN9: =MOD(AK9-1,9)+1 | AO9: =IF(AN9=1,AG9&"-A1-Front",IF(AN9=2,AG9&"-B1-Front",IF(AN9=3,AG9&"-C1-Front",IF(AN9=4,AG9&"-A2-Middle",IF(AN9=5,AG9&"-B2-Middle",IF(AN9=6,AG9&"-A3-Back",IF(AN9=7,AG9&"-B3-Back",IF(AN9=8,AG9&"-C2-Middle",AG9&"-C3-Back")))))))) | AP9: =IF(AH9="Premium","Premium item positioned by score rank within premium bucket",IF(AH9="Standard","Standard item positioned by score rank within standard bucket","Reserve item positioned by score rank within reserve bucket"))
A10: Oats | B10: Food | C10: Food | D10: 3 | E10: 150 | F10: 160 | G10: 3 | H10: Weekly | I10: Weekly | J10: C2-Middle | K10: =Controls!$B$22 | L10: =Controls!$B$20 | M10: =Controls!$B$21 | N10: =ROUND(K10*(L10/12)*(M10/12),2) | O10: =IFERROR(VLOOKUP(C10,Lookup_Tables!$G$4:$H$7,2,FALSE),35) | P10: =IF(O10<=N10,"Fits","Review") | Q10: =ROUND(O10/N10,3) | R10: =Y10&Z10&"-"&AA10 | S10: =IF(E10>=1000,5,IF(E10>=500,4,IF(E10>=250,3,IF(E10>=100,2,1)))) | T10: =IF(F10>=1000,5,IF(F10>=500,4,IF(F10>=250,3,IF(F10>=100,2,1)))) | U10: =IFERROR(VLOOKUP(C10,Lookup_Tables!$A$4:$B$8,2,FALSE),3) | V10: =IFERROR(VLOOKUP(H10,Lookup_Tables!$D$4:$E$11,2,FALSE),2) | W10: =IFERROR(VLOOKUP(I10,Lookup_Tables!$D$4:$E$11,2,FALSE),2) | X10: =ROUND((D10*Controls!$B$4)+(G10*Controls!$B$5)+(S10*Controls!$B$6)+(T10*Controls!$B$7)+(U10*Controls!$B$8)+(MAX(V10,W10)*Controls!$B$9),2) | Y10: =IF(AD10="Bulk","A",IF(X10>=Controls!$B$10,"A",IF(X10>=Controls!$B$11,"B","C"))) | Z10: =IF(OR(D10>=4,G10>=4),1,IF(X10>=Controls!$B$11,2,3)) | AA10: =IF(OR(D10>=4,G10>=4),"Front",IF(X10>=Controls!$B$11,"Middle","Back")) | AB10: =IF(P10="Fits",R10,"Manual Review") | AC10: =IF(AD10="Bulk","Bulk / heavy item -> lower level priority",IF(P10<>"Fits","Review cube fit before assigning location",IF(AND(D10>=4,G10>=4),"High usage + high flow -> front-access priority",IF(X10>=Controls!$B$11,"Medium priority item -> standard access","Low priority / reserve storage")))) | AD10: =IF(OR(C10="Bulk",F10>=Controls!$B$12),"Bulk","Non-Bulk") | AF10: =RANK(X10,$X$4:$X$18,0)+COUNTIF($X$4:X10,X10)-1 | AG10: =IFERROR(VLOOKUP(A10,Lookup_Tables!$L$4:$M$18,2,FALSE),"FOOD") | AH10: =IF(AF10<=5,"Premium",IF(AF10<=11,"Standard","Reserve")) | AI10: =IF(AH10="Premium",IF(AG10="GIK","GIK-A"&MOD(AF10-1,3)+1&"-Front",IF(AG10="FOOD","FOOD-A"&MOD(AF10-1,3)+1&"-Front",IF(AG10="ADDITIONS","ADD-A"&MOD(AF10-1,2)+1&"-Front","GAR-A"&MOD(AF10-1,2)+1&"-Front"))),IF(AH10="Standard",IF(AG10="GIK","GIK-B"&MOD(AF10-1,3)+1&"-Middle",IF(AG10="FOOD","FOOD-B"&MOD(AF10-1,3)+1&"-Middle",IF(AG10="ADDITIONS","ADD-B"&MOD(AF10-1,2)+1&"-Middle","GAR-B"&MOD(AF10-1,2)+1&"-Middle"))),IF(AG10="GIK","GIK-C"&MOD(AF10-1,3)+1&"-Back",IF(AG10="FOOD","FOOD-C"&MOD(AF10-1,3)+1&"-Back",IF(AG10="ADDITIONS","ADD-C"&MOD(AF10-1,2)+1&"-Back","GAR-C"&MOD(AF10-1,2)+1&"-Back"))))) | AJ10: =IF(J10=AI10,"Keep in place",IF(LEFT(J10,3)=LEFT(AI10,3),"Re-slot within same zone","Move to "&AG10&" based on flow, capacity, and layout logic")) | AK10: =IF(AH10="Premium",AF10,IF(AH10="Standard",AF10-5,AF10-11)) | AL10: =IF(AH10="Premium",AG10&"-A"&MOD(AK10-1,3)+1&"-Front",IF(AH10="Standard",AG10&"-B"&MOD(AK10-1,3)+1&"-Middle",AG10&"-C"&MOD(AK10-1,3)+1&"-Back")) | AM10: =IF(AH10="Premium","Premium item distributed across A1/A2/A3 by rank to avoid overloading one slot",IF(AH10="Standard","Standard item distributed across B1/B2/B3 by rank","Reserve item distributed across C1/C2/C3 by rank")) | AN10: =MOD(AK10-1,9)+1 | AO10: =IF(AN10=1,AG10&"-A1-Front",IF(AN10=2,AG10&"-B1-Front",IF(AN10=3,AG10&"-C1-Front",IF(AN10=4,AG10&"-A2-Middle",IF(AN10=5,AG10&"-B2-Middle",IF(AN10=6,AG10&"-A3-Back",IF(AN10=7,AG10&"-B3-Back",IF(AN10=8,AG10&"-C2-Middle",AG10&"-C3-Back")))))))) | AP10: =IF(AH10="Premium","Premium item positioned by score rank within premium bucket",IF(AH10="Standard","Standard item positioned by score rank within standard bucket","Reserve item positioned by score rank within reserve bucket"))
A11: Pancake Mix | B11: Food | C11: Food | D11: 3 | E11: 105 | F11: 140 | G11: 3 | H11: Weekly | I11: Weekly | J11: C2-Back | K11: =Controls!$B$22 | L11: =Controls!$B$20 | M11: =Controls!$B$21 | N11: =ROUND(K11*(L11/12)*(M11/12),2) | O11: =IFERROR(VLOOKUP(C11,Lookup_Tables!$G$4:$H$7,2,FALSE),35) | P11: =IF(O11<=N11,"Fits","Review") | Q11: =ROUND(O11/N11,3) | R11: =Y11&Z11&"-"&AA11 | S11: =IF(E11>=1000,5,IF(E11>=500,4,IF(E11>=250,3,IF(E11>=100,2,1)))) | T11: =IF(F11>=1000,5,IF(F11>=500,4,IF(F11>=250,3,IF(F11>=100,2,1)))) | U11: =IFERROR(VLOOKUP(C11,Lookup_Tables!$A$4:$B$8,2,FALSE),3) | V11: =IFERROR(VLOOKUP(H11,Lookup_Tables!$D$4:$E$11,2,FALSE),2) | W11: =IFERROR(VLOOKUP(I11,Lookup_Tables!$D$4:$E$11,2,FALSE),2) | X11: =ROUND((D11*Controls!$B$4)+(G11*Controls!$B$5)+(S11*Controls!$B$6)+(T11*Controls!$B$7)+(U11*Controls!$B$8)+(MAX(V11,W11)*Controls!$B$9),2) | Y11: =IF(AD11="Bulk","A",IF(X11>=Controls!$B$10,"A",IF(X11>=Controls!$B$11,"B","C"))) | Z11: =IF(OR(D11>=4,G11>=4),1,IF(X11>=Controls!$B$11,2,3)) | AA11: =IF(OR(D11>=4,G11>=4),"Front",IF(X11>=Controls!$B$11,"Middle","Back")) | AB11: =IF(P11="Fits",R11,"Manual Review") | AC11: =IF(AD11="Bulk","Bulk / heavy item -> lower level priority",IF(P11<>"Fits","Review cube fit before assigning location",IF(AND(D11>=4,G11>=4),"High usage + high flow -> front-access priority",IF(X11>=Controls!$B$11,"Medium priority item -> standard access","Low priority / reserve storage")))) | AD11: =IF(OR(C11="Bulk",F11>=Controls!$B$12),"Bulk","Non-Bulk") | AF11: =RANK(X11,$X$4:$X$18,0)+COUNTIF($X$4:X11,X11)-1 | AG11: =IFERROR(VLOOKUP(A11,Lookup_Tables!$L$4:$M$18,2,FALSE),"FOOD") | AH11: =IF(AF11<=5,"Premium",IF(AF11<=11,"Standard","Reserve")) | AI11: =IF(AH11="Premium",IF(AG11="GIK","GIK-A"&MOD(AF11-1,3)+1&"-Front",IF(AG11="FOOD","FOOD-A"&MOD(AF11-1,3)+1&"-Front",IF(AG11="ADDITIONS","ADD-A"&MOD(AF11-1,2)+1&"-Front","GAR-A"&MOD(AF11-1,2)+1&"-Front"))),IF(AH11="Standard",IF(AG11="GIK","GIK-B"&MOD(AF11-1,3)+1&"-Middle",IF(AG11="FOOD","FOOD-B"&MOD(AF11-1,3)+1&"-Middle",IF(AG11="ADDITIONS","ADD-B"&MOD(AF11-1,2)+1&"-Middle","GAR-B"&MOD(AF11-1,2)+1&"-Middle"))),IF(AG11="GIK","GIK-C"&MOD(AF11-1,3)+1&"-Back",IF(AG11="FOOD","FOOD-C"&MOD(AF11-1,3)+1&"-Back",IF(AG11="ADDITIONS","ADD-C"&MOD(AF11-1,2)+1&"-Back","GAR-C"&MOD(AF11-1,2)+1&"-Back"))))) | AJ11: =IF(J11=AI11,"Keep in place",IF(LEFT(J11,3)=LEFT(AI11,3),"Re-slot within same zone","Move to "&AG11&" based on flow, capacity, and layout logic")) | AK11: =IF(AH11="Premium",AF11,IF(AH11="Standard",AF11-5,AF11-11)) | AL11: =IF(AH11="Premium",AG11&"-A"&MOD(AK11-1,3)+1&"-Front",IF(AH11="Standard",AG11&"-B"&MOD(AK11-1,3)+1&"-Middle",AG11&"-C"&MOD(AK11-1,3)+1&"-Back")) | AM11: =IF(AH11="Premium","Premium item distributed across A1/A2/A3 by rank to avoid overloading one slot",IF(AH11="Standard","Standard item distributed across B1/B2/B3 by rank","Reserve item distributed across C1/C2/C3 by rank")) | AN11: =MOD(AK11-1,9)+1 | AO11: =IF(AN11=1,AG11&"-A1-Front",IF(AN11=2,AG11&"-B1-Front",IF(AN11=3,AG11&"-C1-Front",IF(AN11=4,AG11&"-A2-Middle",IF(AN11=5,AG11&"-B2-Middle",IF(AN11=6,AG11&"-A3-Back",IF(AN11=7,AG11&"-B3-Back",IF(AN11=8,AG11&"-C2-Middle",AG11&"-C3-Back")))))))) | AP11: =IF(AH11="Premium","Premium item positioned by score rank within premium bucket",IF(AH11="Standard","Standard item positioned by score rank within standard bucket","Reserve item positioned by score rank within reserve bucket"))
A12: Peaches | B12: Food | C12: Food | D12: 2 | E12: 85 | F12: 130 | G12: 2 | H12: Weekly | I12: Weekly | J12: C3-Back | K12: =Controls!$B$22 | L12: =Controls!$B$20 | M12: =Controls!$B$21 | N12: =ROUND(K12*(L12/12)*(M12/12),2) | O12: =IFERROR(VLOOKUP(C12,Lookup_Tables!$G$4:$H$7,2,FALSE),35) | P12: =IF(O12<=N12,"Fits","Review") | Q12: =ROUND(O12/N12,3) | R12: =Y12&Z12&"-"&AA12 | S12: =IF(E12>=1000,5,IF(E12>=500,4,IF(E12>=250,3,IF(E12>=100,2,1)))) | T12: =IF(F12>=1000,5,IF(F12>=500,4,IF(F12>=250,3,IF(F12>=100,2,1)))) | U12: =IFERROR(VLOOKUP(C12,Lookup_Tables!$A$4:$B$8,2,FALSE),3) | V12: =IFERROR(VLOOKUP(H12,Lookup_Tables!$D$4:$E$11,2,FALSE),2) | W12: =IFERROR(VLOOKUP(I12,Lookup_Tables!$D$4:$E$11,2,FALSE),2) | X12: =ROUND((D12*Controls!$B$4)+(G12*Controls!$B$5)+(S12*Controls!$B$6)+(T12*Controls!$B$7)+(U12*Controls!$B$8)+(MAX(V12,W12)*Controls!$B$9),2) | Y12: =IF(AD12="Bulk","A",IF(X12>=Controls!$B$10,"A",IF(X12>=Controls!$B$11,"B","C"))) | Z12: =IF(OR(D12>=4,G12>=4),1,IF(X12>=Controls!$B$11,2,3)) | AA12: =IF(OR(D12>=4,G12>=4),"Front",IF(X12>=Controls!$B$11,"Middle","Back")) | AB12: =IF(P12="Fits",R12,"Manual Review") | AC12: =IF(AD12="Bulk","Bulk / heavy item -> lower level priority",IF(P12<>"Fits","Review cube fit before assigning location",IF(AND(D12>=4,G12>=4),"High usage + high flow -> front-access priority",IF(X12>=Controls!$B$11,"Medium priority item -> standard access","Low priority / reserve storage")))) | AD12: =IF(OR(C12="Bulk",F12>=Controls!$B$12),"Bulk","Non-Bulk") | AF12: =RANK(X12,$X$4:$X$18,0)+COUNTIF($X$4:X12,X12)-1 | AG12: =IFERROR(VLOOKUP(A12,Lookup_Tables!$L$4:$M$18,2,FALSE),"FOOD") | AH12: =IF(AF12<=5,"Premium",IF(AF12<=11,"Standard","Reserve")) | AI12: =IF(AH12="Premium",IF(AG12="GIK","GIK-A"&MOD(AF12-1,3)+1&"-Front",IF(AG12="FOOD","FOOD-A"&MOD(AF12-1,3)+1&"-Front",IF(AG12="ADDITIONS","ADD-A"&MOD(AF12-1,2)+1&"-Front","GAR-A"&MOD(AF12-1,2)+1&"-Front"))),IF(AH12="Standard",IF(AG12="GIK","GIK-B"&MOD(AF12-1,3)+1&"-Middle",IF(AG12="FOOD","FOOD-B"&MOD(AF12-1,3)+1&"-Middle",IF(AG12="ADDITIONS","ADD-B"&MOD(AF12-1,2)+1&"-Middle","GAR-B"&MOD(AF12-1,2)+1&"-Middle"))),IF(AG12="GIK","GIK-C"&MOD(AF12-1,3)+1&"-Back",IF(AG12="FOOD","FOOD-C"&MOD(AF12-1,3)+1&"-Back",IF(AG12="ADDITIONS","ADD-C"&MOD(AF12-1,2)+1&"-Back","GAR-C"&MOD(AF12-1,2)+1&"-Back"))))) | AJ12: =IF(J12=AI12,"Keep in place",IF(LEFT(J12,3)=LEFT(AI12,3),"Re-slot within same zone","Move to "&AG12&" based on flow, capacity, and layout logic")) | AK12: =IF(AH12="Premium",AF12,IF(AH12="Standard",AF12-5,AF12-11)) | AL12: =IF(AH12="Premium",AG12&"-A"&MOD(AK12-1,3)+1&"-Front",IF(AH12="Standard",AG12&"-B"&MOD(AK12-1,3)+1&"-Middle",AG12&"-C"&MOD(AK12-1,3)+1&"-Back")) | AM12: =IF(AH12="Premium","Premium item distributed across A1/A2/A3 by rank to avoid overloading one slot",IF(AH12="Standard","Standard item distributed across B1/B2/B3 by rank","Reserve item distributed across C1/C2/C3 by rank")) | AN12: =MOD(AK12-1,9)+1 | AO12: =IF(AN12=1,AG12&"-A1-Front",IF(AN12=2,AG12&"-B1-Front",IF(AN12=3,AG12&"-C1-Front",IF(AN12=4,AG12&"-A2-Middle",IF(AN12=5,AG12&"-B2-Middle",IF(AN12=6,AG12&"-A3-Back",IF(AN12=7,AG12&"-B3-Back",IF(AN12=8,AG12&"-C2-Middle",AG12&"-C3-Back")))))))) | AP12: =IF(AH12="Premium","Premium item positioned by score rank within premium bucket",IF(AH12="Standard","Standard item positioned by score rank within standard bucket","Reserve item positioned by score rank within reserve bucket"))
A13: Chili - Beef | B13: Food | C13: Food | D13: 4 | E13: 96 | F13: 180 | G13: 4 | H13: Weekly | I13: Daily | J13: B3-Back | K13: =Controls!$B$22 | L13: =Controls!$B$20 | M13: =Controls!$B$21 | N13: =ROUND(K13*(L13/12)*(M13/12),2) | O13: =IFERROR(VLOOKUP(C13,Lookup_Tables!$G$4:$H$7,2,FALSE),35) | P13: =IF(O13<=N13,"Fits","Review") | Q13: =ROUND(O13/N13,3) | R13: =Y13&Z13&"-"&AA13 | S13: =IF(E13>=1000,5,IF(E13>=500,4,IF(E13>=250,3,IF(E13>=100,2,1)))) | T13: =IF(F13>=1000,5,IF(F13>=500,4,IF(F13>=250,3,IF(F13>=100,2,1)))) | U13: =IFERROR(VLOOKUP(C13,Lookup_Tables!$A$4:$B$8,2,FALSE),3) | V13: =IFERROR(VLOOKUP(H13,Lookup_Tables!$D$4:$E$11,2,FALSE),2) | W13: =IFERROR(VLOOKUP(I13,Lookup_Tables!$D$4:$E$11,2,FALSE),2) | X13: =ROUND((D13*Controls!$B$4)+(G13*Controls!$B$5)+(S13*Controls!$B$6)+(T13*Controls!$B$7)+(U13*Controls!$B$8)+(MAX(V13,W13)*Controls!$B$9),2) | Y13: =IF(AD13="Bulk","A",IF(X13>=Controls!$B$10,"A",IF(X13>=Controls!$B$11,"B","C"))) | Z13: =IF(OR(D13>=4,G13>=4),1,IF(X13>=Controls!$B$11,2,3)) | AA13: =IF(OR(D13>=4,G13>=4),"Front",IF(X13>=Controls!$B$11,"Middle","Back")) | AB13: =IF(P13="Fits",R13,"Manual Review") | AC13: =IF(AD13="Bulk","Bulk / heavy item -> lower level priority",IF(P13<>"Fits","Review cube fit before assigning location",IF(AND(D13>=4,G13>=4),"High usage + high flow -> front-access priority",IF(X13>=Controls!$B$11,"Medium priority item -> standard access","Low priority / reserve storage")))) | AD13: =IF(OR(C13="Bulk",F13>=Controls!$B$12),"Bulk","Non-Bulk") | AF13: =RANK(X13,$X$4:$X$18,0)+COUNTIF($X$4:X13,X13)-1 | AG13: =IFERROR(VLOOKUP(A13,Lookup_Tables!$L$4:$M$18,2,FALSE),"FOOD") | AH13: =IF(AF13<=5,"Premium",IF(AF13<=11,"Standard","Reserve")) | AI13: =IF(AH13="Premium",IF(AG13="GIK","GIK-A"&MOD(AF13-1,3)+1&"-Front",IF(AG13="FOOD","FOOD-A"&MOD(AF13-1,3)+1&"-Front",IF(AG13="ADDITIONS","ADD-A"&MOD(AF13-1,2)+1&"-Front","GAR-A"&MOD(AF13-1,2)+1&"-Front"))),IF(AH13="Standard",IF(AG13="GIK","GIK-B"&MOD(AF13-1,3)+1&"-Middle",IF(AG13="FOOD","FOOD-B"&MOD(AF13-1,3)+1&"-Middle",IF(AG13="ADDITIONS","ADD-B"&MOD(AF13-1,2)+1&"-Middle","GAR-B"&MOD(AF13-1,2)+1&"-Middle"))),IF(AG13="GIK","GIK-C"&MOD(AF13-1,3)+1&"-Back",IF(AG13="FOOD","FOOD-C"&MOD(AF13-1,3)+1&"-Back",IF(AG13="ADDITIONS","ADD-C"&MOD(AF13-1,2)+1&"-Back","GAR-C"&MOD(AF13-1,2)+1&"-Back"))))) | AJ13: =IF(J13=AI13,"Keep in place",IF(LEFT(J13,3)=LEFT(AI13,3),"Re-slot within same zone","Move to "&AG13&" based on flow, capacity, and layout logic")) | AK13: =IF(AH13="Premium",AF13,IF(AH13="Standard",AF13-5,AF13-11)) | AL13: =IF(AH13="Premium",AG13&"-A"&MOD(AK13-1,3)+1&"-Front",IF(AH13="Standard",AG13&"-B"&MOD(AK13-1,3)+1&"-Middle",AG13&"-C"&MOD(AK13-1,3)+1&"-Back")) | AM13: =IF(AH13="Premium","Premium item distributed across A1/A2/A3 by rank to avoid overloading one slot",IF(AH13="Standard","Standard item distributed across B1/B2/B3 by rank","Reserve item distributed across C1/C2/C3 by rank")) | AN13: =MOD(AK13-1,9)+1 | AO13: =IF(AN13=1,AG13&"-A1-Front",IF(AN13=2,AG13&"-B1-Front",IF(AN13=3,AG13&"-C1-Front",IF(AN13=4,AG13&"-A2-Middle",IF(AN13=5,AG13&"-B2-Middle",IF(AN13=6,AG13&"-A3-Back",IF(AN13=7,AG13&"-B3-Back",IF(AN13=8,AG13&"-C2-Middle",AG13&"-C3-Back")))))))) | AP13: =IF(AH13="Premium","Premium item positioned by score rank within premium bucket",IF(AH13="Standard","Standard item positioned by score rank within standard bucket","Reserve item positioned by score rank within reserve bucket"))
A14: Mixed Vegetables | B14: Food | C14: Food | D14: 3 | E14: 85 | F14: 120 | G14: 3 | H14: Weekly | I14: Weekly | J14: C3-Middle | K14: =Controls!$B$22 | L14: =Controls!$B$20 | M14: =Controls!$B$21 | N14: =ROUND(K14*(L14/12)*(M14/12),2) | O14: =IFERROR(VLOOKUP(C14,Lookup_Tables!$G$4:$H$7,2,FALSE),35) | P14: =IF(O14<=N14,"Fits","Review") | Q14: =ROUND(O14/N14,3) | R14: =Y14&Z14&"-"&AA14 | S14: =IF(E14>=1000,5,IF(E14>=500,4,IF(E14>=250,3,IF(E14>=100,2,1)))) | T14: =IF(F14>=1000,5,IF(F14>=500,4,IF(F14>=250,3,IF(F14>=100,2,1)))) | U14: =IFERROR(VLOOKUP(C14,Lookup_Tables!$A$4:$B$8,2,FALSE),3) | V14: =IFERROR(VLOOKUP(H14,Lookup_Tables!$D$4:$E$11,2,FALSE),2) | W14: =IFERROR(VLOOKUP(I14,Lookup_Tables!$D$4:$E$11,2,FALSE),2) | X14: =ROUND((D14*Controls!$B$4)+(G14*Controls!$B$5)+(S14*Controls!$B$6)+(T14*Controls!$B$7)+(U14*Controls!$B$8)+(MAX(V14,W14)*Controls!$B$9),2) | Y14: =IF(AD14="Bulk","A",IF(X14>=Controls!$B$10,"A",IF(X14>=Controls!$B$11,"B","C"))) | Z14: =IF(OR(D14>=4,G14>=4),1,IF(X14>=Controls!$B$11,2,3)) | AA14: =IF(OR(D14>=4,G14>=4),"Front",IF(X14>=Controls!$B$11,"Middle","Back")) | AB14: =IF(P14="Fits",R14,"Manual Review") | AC14: =IF(AD14="Bulk","Bulk / heavy item -> lower level priority",IF(P14<>"Fits","Review cube fit before assigning location",IF(AND(D14>=4,G14>=4),"High usage + high flow -> front-access priority",IF(X14>=Controls!$B$11,"Medium priority item -> standard access","Low priority / reserve storage")))) | AD14: =IF(OR(C14="Bulk",F14>=Controls!$B$12),"Bulk","Non-Bulk") | AF14: =RANK(X14,$X$4:$X$18,0)+COUNTIF($X$4:X14,X14)-1 | AG14: =IFERROR(VLOOKUP(A14,Lookup_Tables!$L$4:$M$18,2,FALSE),"FOOD") | AH14: =IF(AF14<=5,"Premium",IF(AF14<=11,"Standard","Reserve")) | AI14: =IF(AH14="Premium",IF(AG14="GIK","GIK-A"&MOD(AF14-1,3)+1&"-Front",IF(AG14="FOOD","FOOD-A"&MOD(AF14-1,3)+1&"-Front",IF(AG14="ADDITIONS","ADD-A"&MOD(AF14-1,2)+1&"-Front","GAR-A"&MOD(AF14-1,2)+1&"-Front"))),IF(AH14="Standard",IF(AG14="GIK","GIK-B"&MOD(AF14-1,3)+1&"-Middle",IF(AG14="FOOD","FOOD-B"&MOD(AF14-1,3)+1&"-Middle",IF(AG14="ADDITIONS","ADD-B"&MOD(AF14-1,2)+1&"-Middle","GAR-B"&MOD(AF14-1,2)+1&"-Middle"))),IF(AG14="GIK","GIK-C"&MOD(AF14-1,3)+1&"-Back",IF(AG14="FOOD","FOOD-C"&MOD(AF14-1,3)+1&"-Back",IF(AG14="ADDITIONS","ADD-C"&MOD(AF14-1,2)+1&"-Back","GAR-C"&MOD(AF14-1,2)+1&"-Back"))))) | AJ14: =IF(J14=AI14,"Keep in place",IF(LEFT(J14,3)=LEFT(AI14,3),"Re-slot within same zone","Move to "&AG14&" based on flow, capacity, and layout logic")) | AK14: =IF(AH14="Premium",AF14,IF(AH14="Standard",AF14-5,AF14-11)) | AL14: =IF(AH14="Premium",AG14&"-A"&MOD(AK14-1,3)+1&"-Front",IF(AH14="Standard",AG14&"-B"&MOD(AK14-1,3)+1&"-Middle",AG14&"-C"&MOD(AK14-1,3)+1&"-Back")) | AM14: =IF(AH14="Premium","Premium item distributed across A1/A2/A3 by rank to avoid overloading one slot",IF(AH14="Standard","Standard item distributed across B1/B2/B3 by rank","Reserve item distributed across C1/C2/C3 by rank")) | AN14: =MOD(AK14-1,9)+1 | AO14: =IF(AN14=1,AG14&"-A1-Front",IF(AN14=2,AG14&"-B1-Front",IF(AN14=3,AG14&"-C1-Front",IF(AN14=4,AG14&"-A2-Middle",IF(AN14=5,AG14&"-B2-Middle",IF(AN14=6,AG14&"-A3-Back",IF(AN14=7,AG14&"-B3-Back",IF(AN14=8,AG14&"-C2-Middle",AG14&"-C3-Back")))))))) | AP14: =IF(AH14="Premium","Premium item positioned by score rank within premium bucket",IF(AH14="Standard","Standard item positioned by score rank within standard bucket","Reserve item positioned by score rank within reserve bucket"))
A15: Green Beans | B15: Food | C15: Food | D15: 3 | E15: 102 | F15: 150 | G15: 3 | H15: Weekly | I15: Weekly | J15: C2-Front | K15: =Controls!$B$22 | L15: =Controls!$B$20 | M15: =Controls!$B$21 | N15: =ROUND(K15*(L15/12)*(M15/12),2) | O15: =IFERROR(VLOOKUP(C15,Lookup_Tables!$G$4:$H$7,2,FALSE),35) | P15: =IF(O15<=N15,"Fits","Review") | Q15: =ROUND(O15/N15,3) | R15: =Y15&Z15&"-"&AA15 | S15: =IF(E15>=1000,5,IF(E15>=500,4,IF(E15>=250,3,IF(E15>=100,2,1)))) | T15: =IF(F15>=1000,5,IF(F15>=500,4,IF(F15>=250,3,IF(F15>=100,2,1)))) | U15: =IFERROR(VLOOKUP(C15,Lookup_Tables!$A$4:$B$8,2,FALSE),3) | V15: =IFERROR(VLOOKUP(H15,Lookup_Tables!$D$4:$E$11,2,FALSE),2) | W15: =IFERROR(VLOOKUP(I15,Lookup_Tables!$D$4:$E$11,2,FALSE),2) | X15: =ROUND((D15*Controls!$B$4)+(G15*Controls!$B$5)+(S15*Controls!$B$6)+(T15*Controls!$B$7)+(U15*Controls!$B$8)+(MAX(V15,W15)*Controls!$B$9),2) | Y15: =IF(AD15="Bulk","A",IF(X15>=Controls!$B$10,"A",IF(X15>=Controls!$B$11,"B","C"))) | Z15: =IF(OR(D15>=4,G15>=4),1,IF(X15>=Controls!$B$11,2,3)) | AA15: =IF(OR(D15>=4,G15>=4),"Front",IF(X15>=Controls!$B$11,"Middle","Back")) | AB15: =IF(P15="Fits",R15,"Manual Review") | AC15: =IF(AD15="Bulk","Bulk / heavy item -> lower level priority",IF(P15<>"Fits","Review cube fit before assigning location",IF(AND(D15>=4,G15>=4),"High usage + high flow -> front-access priority",IF(X15>=Controls!$B$11,"Medium priority item -> standard access","Low priority / reserve storage")))) | AD15: =IF(OR(C15="Bulk",F15>=Controls!$B$12),"Bulk","Non-Bulk") | AF15: =RANK(X15,$X$4:$X$18,0)+COUNTIF($X$4:X15,X15)-1 | AG15: =IFERROR(VLOOKUP(A15,Lookup_Tables!$L$4:$M$18,2,FALSE),"FOOD") | AH15: =IF(AF15<=5,"Premium",IF(AF15<=11,"Standard","Reserve")) | AI15: =IF(AH15="Premium",IF(AG15="GIK","GIK-A"&MOD(AF15-1,3)+1&"-Front",IF(AG15="FOOD","FOOD-A"&MOD(AF15-1,3)+1&"-Front",IF(AG15="ADDITIONS","ADD-A"&MOD(AF15-1,2)+1&"-Front","GAR-A"&MOD(AF15-1,2)+1&"-Front"))),IF(AH15="Standard",IF(AG15="GIK","GIK-B"&MOD(AF15-1,3)+1&"-Middle",IF(AG15="FOOD","FOOD-B"&MOD(AF15-1,3)+1&"-Middle",IF(AG15="ADDITIONS","ADD-B"&MOD(AF15-1,2)+1&"-Middle","GAR-B"&MOD(AF15-1,2)+1&"-Middle"))),IF(AG15="GIK","GIK-C"&MOD(AF15-1,3)+1&"-Back",IF(AG15="FOOD","FOOD-C"&MOD(AF15-1,3)+1&"-Back",IF(AG15="ADDITIONS","ADD-C"&MOD(AF15-1,2)+1&"-Back","GAR-C"&MOD(AF15-1,2)+1&"-Back"))))) | AJ15: =IF(J15=AI15,"Keep in place",IF(LEFT(J15,3)=LEFT(AI15,3),"Re-slot within same zone","Move to "&AG15&" based on flow, capacity, and layout logic")) | AK15: =IF(AH15="Premium",AF15,IF(AH15="Standard",AF15-5,AF15-11)) | AL15: =IF(AH15="Premium",AG15&"-A"&MOD(AK15-1,3)+1&"-Front",IF(AH15="Standard",AG15&"-B"&MOD(AK15-1,3)+1&"-Middle",AG15&"-C"&MOD(AK15-1,3)+1&"-Back")) | AM15: =IF(AH15="Premium","Premium item distributed across A1/A2/A3 by rank to avoid overloading one slot",IF(AH15="Standard","Standard item distributed across B1/B2/B3 by rank","Reserve item distributed across C1/C2/C3 by rank")) | AN15: =MOD(AK15-1,9)+1 | AO15: =IF(AN15=1,AG15&"-A1-Front",IF(AN15=2,AG15&"-B1-Front",IF(AN15=3,AG15&"-C1-Front",IF(AN15=4,AG15&"-A2-Middle",IF(AN15=5,AG15&"-B2-Middle",IF(AN15=6,AG15&"-A3-Back",IF(AN15=7,AG15&"-B3-Back",IF(AN15=8,AG15&"-C2-Middle",AG15&"-C3-Back")))))))) | AP15: =IF(AH15="Premium","Premium item positioned by score rank within premium bucket",IF(AH15="Standard","Standard item positioned by score rank within standard bucket","Reserve item positioned by score rank within reserve bucket"))
A16: Chicken Leg Quarters | B16: Meat | C16: Meat | D16: 5 | E16: 960 | F16: 960 | G16: 5 | H16: Biweekly | I16: Daily | J16: B3-Front | K16: =Controls!$B$22 | L16: =Controls!$B$20 | M16: =Controls!$B$21 | N16: =ROUND(K16*(L16/12)*(M16/12),2) | O16: =IFERROR(VLOOKUP(C16,Lookup_Tables!$G$4:$H$7,2,FALSE),35) | P16: =IF(O16<=N16,"Fits","Review") | Q16: =ROUND(O16/N16,3) | R16: =Y16&Z16&"-"&AA16 | S16: =IF(E16>=1000,5,IF(E16>=500,4,IF(E16>=250,3,IF(E16>=100,2,1)))) | T16: =IF(F16>=1000,5,IF(F16>=500,4,IF(F16>=250,3,IF(F16>=100,2,1)))) | U16: =IFERROR(VLOOKUP(C16,Lookup_Tables!$A$4:$B$8,2,FALSE),3) | V16: =IFERROR(VLOOKUP(H16,Lookup_Tables!$D$4:$E$11,2,FALSE),2) | W16: =IFERROR(VLOOKUP(I16,Lookup_Tables!$D$4:$E$11,2,FALSE),2) | X16: =ROUND((D16*Controls!$B$4)+(G16*Controls!$B$5)+(S16*Controls!$B$6)+(T16*Controls!$B$7)+(U16*Controls!$B$8)+(MAX(V16,W16)*Controls!$B$9),2) | Y16: =IF(AD16="Bulk","A",IF(X16>=Controls!$B$10,"A",IF(X16>=Controls!$B$11,"B","C"))) | Z16: =IF(OR(D16>=4,G16>=4),1,IF(X16>=Controls!$B$11,2,3)) | AA16: =IF(OR(D16>=4,G16>=4),"Front",IF(X16>=Controls!$B$11,"Middle","Back")) | AB16: =IF(P16="Fits",R16,"Manual Review") | AC16: =IF(AD16="Bulk","Bulk / heavy item -> lower level priority",IF(P16<>"Fits","Review cube fit before assigning location",IF(AND(D16>=4,G16>=4),"High usage + high flow -> front-access priority",IF(X16>=Controls!$B$11,"Medium priority item -> standard access","Low priority / reserve storage")))) | AD16: =IF(OR(C16="Bulk",F16>=Controls!$B$12),"Bulk","Non-Bulk") | AE16: Fresh/time-sensitive item assumed to move within 3 days. | AF16: =RANK(X16,$X$4:$X$18,0)+COUNTIF($X$4:X16,X16)-1 | AG16: =IFERROR(VLOOKUP(A16,Lookup_Tables!$L$4:$M$18,2,FALSE),"FOOD") | AH16: =IF(AF16<=5,"Premium",IF(AF16<=11,"Standard","Reserve")) | AI16: =IF(AH16="Premium",IF(AG16="GIK","GIK-A"&MOD(AF16-1,3)+1&"-Front",IF(AG16="FOOD","FOOD-A"&MOD(AF16-1,3)+1&"-Front",IF(AG16="ADDITIONS","ADD-A"&MOD(AF16-1,2)+1&"-Front","GAR-A"&MOD(AF16-1,2)+1&"-Front"))),IF(AH16="Standard",IF(AG16="GIK","GIK-B"&MOD(AF16-1,3)+1&"-Middle",IF(AG16="FOOD","FOOD-B"&MOD(AF16-1,3)+1&"-Middle",IF(AG16="ADDITIONS","ADD-B"&MOD(AF16-1,2)+1&"-Middle","GAR-B"&MOD(AF16-1,2)+1&"-Middle"))),IF(AG16="GIK","GIK-C"&MOD(AF16-1,3)+1&"-Back",IF(AG16="FOOD","FOOD-C"&MOD(AF16-1,3)+1&"-Back",IF(AG16="ADDITIONS","ADD-C"&MOD(AF16-1,2)+1&"-Back","GAR-C"&MOD(AF16-1,2)+1&"-Back"))))) | AJ16: =IF(J16=AI16,"Keep in place",IF(LEFT(J16,3)=LEFT(AI16,3),"Re-slot within same zone","Move to "&AG16&" based on flow, capacity, and layout logic")) | AK16: =IF(AH16="Premium",AF16,IF(AH16="Standard",AF16-5,AF16-11)) | AL16: =IF(AH16="Premium",AG16&"-A"&MOD(AK16-1,3)+1&"-Front",IF(AH16="Standard",AG16&"-B"&MOD(AK16-1,3)+1&"-Middle",AG16&"-C"&MOD(AK16-1,3)+1&"-Back")) | AM16: =IF(AH16="Premium","Premium item distributed across A1/A2/A3 by rank to avoid overloading one slot",IF(AH16="Standard","Standard item distributed across B1/B2/B3 by rank","Reserve item distributed across C1/C2/C3 by rank")) | AN16: =MOD(AK16-1,9)+1 | AO16: =IF(AN16=1,AG16&"-A1-Front",IF(AN16=2,AG16&"-B1-Front",IF(AN16=3,AG16&"-C1-Front",IF(AN16=4,AG16&"-A2-Middle",IF(AN16=5,AG16&"-B2-Middle",IF(AN16=6,AG16&"-A3-Back",IF(AN16=7,AG16&"-B3-Back",IF(AN16=8,AG16&"-C2-Middle",AG16&"-C3-Back")))))))) | AP16: =IF(AH16="Premium","Premium item positioned by score rank within premium bucket",IF(AH16="Standard","Standard item positioned by score rank within standard bucket","Reserve item positioned by score rank within reserve bucket"))
A17: Ground Beef | B17: Meat | C17: Meat | D17: 4 | E17: 19220 | F17: 4000 | G17: 5 | H17: Monthly | I17: Daily | J17: C1-Back | K17: =Controls!$B$22 | L17: =Controls!$B$20 | M17: =Controls!$B$21 | N17: =ROUND(K17*(L17/12)*(M17/12),2) | O17: =IFERROR(VLOOKUP(C17,Lookup_Tables!$G$4:$H$7,2,FALSE),35) | P17: =IF(O17<=N17,"Fits","Review") | Q17: =ROUND(O17/N17,3) | R17: =Y17&Z17&"-"&AA17 | S17: =IF(E17>=1000,5,IF(E17>=500,4,IF(E17>=250,3,IF(E17>=100,2,1)))) | T17: =IF(F17>=1000,5,IF(F17>=500,4,IF(F17>=250,3,IF(F17>=100,2,1)))) | U17: =IFERROR(VLOOKUP(C17,Lookup_Tables!$A$4:$B$8,2,FALSE),3) | V17: =IFERROR(VLOOKUP(H17,Lookup_Tables!$D$4:$E$11,2,FALSE),2) | W17: =IFERROR(VLOOKUP(I17,Lookup_Tables!$D$4:$E$11,2,FALSE),2) | X17: =ROUND((D17*Controls!$B$4)+(G17*Controls!$B$5)+(S17*Controls!$B$6)+(T17*Controls!$B$7)+(U17*Controls!$B$8)+(MAX(V17,W17)*Controls!$B$9),2) | Y17: =IF(AD17="Bulk","A",IF(X17>=Controls!$B$10,"A",IF(X17>=Controls!$B$11,"B","C"))) | Z17: =IF(OR(D17>=4,G17>=4),1,IF(X17>=Controls!$B$11,2,3)) | AA17: =IF(OR(D17>=4,G17>=4),"Front",IF(X17>=Controls!$B$11,"Middle","Back")) | AB17: =IF(P17="Fits",R17,"Manual Review") | AC17: =IF(AD17="Bulk","Bulk / heavy item -> lower level priority",IF(P17<>"Fits","Review cube fit before assigning location",IF(AND(D17>=4,G17>=4),"High usage + high flow -> front-access priority",IF(X17>=Controls!$B$11,"Medium priority item -> standard access","Low priority / reserve storage")))) | AD17: =IF(OR(C17="Bulk",F17>=Controls!$B$12),"Bulk","Non-Bulk") | AE17: Fresh/time-sensitive item assumed to move within 3 days. | AF17: =RANK(X17,$X$4:$X$18,0)+COUNTIF($X$4:X17,X17)-1 | AG17: =IFERROR(VLOOKUP(A17,Lookup_Tables!$L$4:$M$18,2,FALSE),"FOOD") | AH17: =IF(AF17<=5,"Premium",IF(AF17<=11,"Standard","Reserve")) | AI17: =IF(AH17="Premium",IF(AG17="GIK","GIK-A"&MOD(AF17-1,3)+1&"-Front",IF(AG17="FOOD","FOOD-A"&MOD(AF17-1,3)+1&"-Front",IF(AG17="ADDITIONS","ADD-A"&MOD(AF17-1,2)+1&"-Front","GAR-A"&MOD(AF17-1,2)+1&"-Front"))),IF(AH17="Standard",IF(AG17="GIK","GIK-B"&MOD(AF17-1,3)+1&"-Middle",IF(AG17="FOOD","FOOD-B"&MOD(AF17-1,3)+1&"-Middle",IF(AG17="ADDITIONS","ADD-B"&MOD(AF17-1,2)+1&"-Middle","GAR-B"&MOD(AF17-1,2)+1&"-Middle"))),IF(AG17="GIK","GIK-C"&MOD(AF17-1,3)+1&"-Back",IF(AG17="FOOD","FOOD-C"&MOD(AF17-1,3)+1&"-Back",IF(AG17="ADDITIONS","ADD-C"&MOD(AF17-1,2)+1&"-Back","GAR-C"&MOD(AF17-1,2)+1&"-Back"))))) | AJ17: =IF(J17=AI17,"Keep in place",IF(LEFT(J17,3)=LEFT(AI17,3),"Re-slot within same zone","Move to "&AG17&" based on flow, capacity, and layout logic")) | AK17: =IF(AH17="Premium",AF17,IF(AH17="Standard",AF17-5,AF17-11)) | AL17: =IF(AH17="Premium",AG17&"-A"&MOD(AK17-1,3)+1&"-Front",IF(AH17="Standard",AG17&"-B"&MOD(AK17-1,3)+1&"-Middle",AG17&"-C"&MOD(AK17-1,3)+1&"-Back")) | AM17: =IF(AH17="Premium","Premium item distributed across A1/A2/A3 by rank to avoid overloading one slot",IF(AH17="Standard","Standard item distributed across B1/B2/B3 by rank","Reserve item distributed across C1/C2/C3 by rank")) | AN17: =MOD(AK17-1,9)+1 | AO17: =IF(AN17=1,AG17&"-A1-Front",IF(AN17=2,AG17&"-B1-Front",IF(AN17=3,AG17&"-C1-Front",IF(AN17=4,AG17&"-A2-Middle",IF(AN17=5,AG17&"-B2-Middle",IF(AN17=6,AG17&"-A3-Back",IF(AN17=7,AG17&"-B3-Back",IF(AN17=8,AG17&"-C2-Middle",AG17&"-C3-Back")))))))) | AP17: =IF(AH17="Premium","Premium item positioned by score rank within premium bucket",IF(AH17="Standard","Standard item positioned by score rank within standard bucket","Reserve item positioned by score rank within reserve bucket"))
A18: Macaroni in Tomato Sauce | B18: Food | C18: Food | D18: 4 | E18: 161 | F18: 220 | G18: 4 | H18: Weekly | I18: Daily | J18: B2-Back | K18: =Controls!$B$22 | L18: =Controls!$B$20 | M18: =Controls!$B$21 | N18: =ROUND(K18*(L18/12)*(M18/12),2) | O18: =IFERROR(VLOOKUP(C18,Lookup_Tables!$G$4:$H$7,2,FALSE),35) | P18: =IF(O18<=N18,"Fits","Review") | Q18: =ROUND(O18/N18,3) | R18: =Y18&Z18&"-"&AA18 | S18: =IF(E18>=1000,5,IF(E18>=500,4,IF(E18>=250,3,IF(E18>=100,2,1)))) | T18: =IF(F18>=1000,5,IF(F18>=500,4,IF(F18>=250,3,IF(F18>=100,2,1)))) | U18: =IFERROR(VLOOKUP(C18,Lookup_Tables!$A$4:$B$8,2,FALSE),3) | V18: =IFERROR(VLOOKUP(H18,Lookup_Tables!$D$4:$E$11,2,FALSE),2) | W18: =IFERROR(VLOOKUP(I18,Lookup_Tables!$D$4:$E$11,2,FALSE),2) | X18: =ROUND((D18*Controls!$B$4)+(G18*Controls!$B$5)+(S18*Controls!$B$6)+(T18*Controls!$B$7)+(U18*Controls!$B$8)+(MAX(V18,W18)*Controls!$B$9),2) | Y18: =IF(AD18="Bulk","A",IF(X18>=Controls!$B$10,"A",IF(X18>=Controls!$B$11,"B","C"))) | Z18: =IF(OR(D18>=4,G18>=4),1,IF(X18>=Controls!$B$11,2,3)) | AA18: =IF(OR(D18>=4,G18>=4),"Front",IF(X18>=Controls!$B$11,"Middle","Back")) | AB18: =IF(P18="Fits",R18,"Manual Review") | AC18: =IF(AD18="Bulk","Bulk / heavy item -> lower level priority",IF(P18<>"Fits","Review cube fit before assigning location",IF(AND(D18>=4,G18>=4),"High usage + high flow -> front-access priority",IF(X18>=Controls!$B$11,"Medium priority item -> standard access","Low priority / reserve storage")))) | AD18: =IF(OR(C18="Bulk",F18>=Controls!$B$12),"Bulk","Non-Bulk") | AF18: =RANK(X18,$X$4:$X$18,0)+COUNTIF($X$4:X18,X18)-1 | AG18: =IFERROR(VLOOKUP(A18,Lookup_Tables!$L$4:$M$18,2,FALSE),"FOOD") | AH18: =IF(AF18<=5,"Premium",IF(AF18<=11,"Standard","Reserve")) | AI18: =IF(AH18="Premium",IF(AG18="GIK","GIK-A"&MOD(AF18-1,3)+1&"-Front",IF(AG18="FOOD","FOOD-A"&MOD(AF18-1,3)+1&"-Front",IF(AG18="ADDITIONS","ADD-A"&MOD(AF18-1,2)+1&"-Front","GAR-A"&MOD(AF18-1,2)+1&"-Front"))),IF(AH18="Standard",IF(AG18="GIK","GIK-B"&MOD(AF18-1,3)+1&"-Middle",IF(AG18="FOOD","FOOD-B"&MOD(AF18-1,3)+1&"-Middle",IF(AG18="ADDITIONS","ADD-B"&MOD(AF18-1,2)+1&"-Middle","GAR-B"&MOD(AF18-1,2)+1&"-Middle"))),IF(AG18="GIK","GIK-C"&MOD(AF18-1,3)+1&"-Back",IF(AG18="FOOD","FOOD-C"&MOD(AF18-1,3)+1&"-Back",IF(AG18="ADDITIONS","ADD-C"&MOD(AF18-1,2)+1&"-Back","GAR-C"&MOD(AF18-1,2)+1&"-Back"))))) | AJ18: =IF(J18=AI18,"Keep in place",IF(LEFT(J18,3)=LEFT(AI18,3),"Re-slot within same zone","Move to "&AG18&" based on flow, capacity, and layout logic")) | AK18: =IF(AH18="Premium",AF18,IF(AH18="Standard",AF18-5,AF18-11)) | AL18: =IF(AH18="Premium",AG18&"-A"&MOD(AK18-1,3)+1&"-Front",IF(AH18="Standard",AG18&"-B"&MOD(AK18-1,3)+1&"-Middle",AG18&"-C"&MOD(AK18-1,3)+1&"-Back")) | AM18: =IF(AH18="Premium","Premium item distributed across A1/A2/A3 by rank to avoid overloading one slot",IF(AH18="Standard","Standard item distributed across B1/B2/B3 by rank","Reserve item distributed across C1/C2/C3 by rank")) | AN18: =MOD(AK18-1,9)+1 | AO18: =IF(AN18=1,AG18&"-A1-Front",IF(AN18=2,AG18&"-B1-Front",IF(AN18=3,AG18&"-C1-Front",IF(AN18=4,AG18&"-A2-Middle",IF(AN18=5,AG18&"-B2-Middle",IF(AN18=6,AG18&"-A3-Back",IF(AN18=7,AG18&"-B3-Back",IF(AN18=8,AG18&"-C2-Middle",AG18&"-C3-Back")))))))) | AP18: =IF(AH18="Premium","Premium item positioned by score rank within premium bucket",IF(AH18="Standard","Standard item positioned by score rank within standard bucket","Reserve item positioned by score rank within reserve bucket"))
A19: Model Summary | B19: Items | C19: =COUNTA(A4:A18) | D19: Re-slot | E19: =COUNTIF(AC4:AC18,"*priority*")+COUNTIF(AC4:AC18,"Review*") | F19: Bulk Items | G19: =COUNTIF(AD4:AD18,"Bulk") | H19: A-Level | I19: =COUNTIF(Y4:Y18,"A") | K19: =Controls!$B$22 | L19: =Controls!$B$20 | M19: =Controls!$B$21 | N19: =ROUND(K19*(L19/12)*(M19/12),2) | O19: =VLOOKUP(C19,Lookup_Tables!$G$4:$H$7,2,FALSE) | P19: =IF(O19<=N19,"Fits","Review") | Q19: =ROUND(O19/N19,3) | R19: =V19&W19&"-"&X19 | S19: =IF(E19>=1000,5,IF(E19>=500,4,IF(E19>=250,3,IF(E19>=100,2,1)))) | T19: =IF(F19>=1000,5,IF(F19>=500,4,IF(F19>=250,3,IF(F19>=100,2,1)))) | U19: =VLOOKUP(C19,Lookup_Tables!A:B,2,FALSE) | V19: =VLOOKUP(H19,Lookup_Tables!D:E,2,FALSE) | W19: =VLOOKUP(I19,Lookup_Tables!D:E,2,FALSE) | X19: =ROUND((D19*Controls!$B$4)+(G19*Controls!$B$5)+(K19*Controls!$B$6)+(L19*Controls!$B$7)+(M19*Controls!$B$8)+(MAX(N19,O19)*Controls!$B$9),2) | Y19: =IF(AND(C19="Bulk",F19>=Controls!$B$12),"A",IF(P19>=Controls!$B$10,"A",IF(P19>=Controls!$B$11,"B","C"))) | Z19: =IF(OR(D19>=4,G19>=4),1,IF(P19>=Controls!$B$11,2,3)) | AA19: =IF(OR(D19>=4,G19>=4),"Front",IF(P19>=Controls!$B$11,"Middle","Back")) | AB19: =Q19&R19&"-"&S19 | AC19: =IF(T19=J19,"Keep current slot","Re-slot for better access / flow")
A20: Avg Storage Priority Score | B20: 3.68 | K20: =Controls!$B$22 | L20: =Controls!$B$20 | M20: =Controls!$B$21 | N20: =ROUND(K20*(L20/12)*(M20/12),2) | O20: =VLOOKUP(C20,Lookup_Tables!$G$4:$H$7,2,FALSE) | P20: =IF(O20<=N20,"Fits","Review") | Q20: =ROUND(O20/N20,3) | R20: =V20&W20&"-"&X20 | S20: =IF(E20>=1000,5,IF(E20>=500,4,IF(E20>=250,3,IF(E20>=100,2,1)))) | T20: =IF(F20>=1000,5,IF(F20>=500,4,IF(F20>=250,3,IF(F20>=100,2,1)))) | U20: =VLOOKUP(C20,Lookup_Tables!A:B,2,FALSE) | V20: =VLOOKUP(H20,Lookup_Tables!D:E,2,FALSE) | W20: =VLOOKUP(I20,Lookup_Tables!D:E,2,FALSE) | X20: =ROUND((D20*Controls!$B$4)+(G20*Controls!$B$5)+(K20*Controls!$B$6)+(L20*Controls!$B$7)+(M20*Controls!$B$8)+(MAX(N20,O20)*Controls!$B$9),2) | Y20: =IF(AND(C20="Bulk",F20>=Controls!$B$12),"A",IF(P20>=Controls!$B$10,"A",IF(P20>=Controls!$B$11,"B","C"))) | Z20: =IF(OR(D20>=4,G20>=4),1,IF(P20>=Controls!$B$11,2,3)) | AA20: =IF(OR(D20>=4,G20>=4),"Front",IF(P20>=Controls!$B$11,"Middle","Back")) | AB20: =Q20&R20&"-"&S20 | AC20: =IF(T20=J20,"Keep current slot","Re-slot for better access / flow")
A21: Re-slot Candidates | B21: 14 | K21: =Controls!$B$22 | L21: =Controls!$B$20 | M21: =Controls!$B$21 | N21: =ROUND(K21*(L21/12)*(M21/12),2) | O21: =VLOOKUP(C21,Lookup_Tables!$G$4:$H$7,2,FALSE) | P21: =IF(O21<=N21,"Fits","Review") | Q21: =ROUND(O21/N21,3) | R21: =V21&W21&"-"&X21 | S21: =IF(E21>=1000,5,IF(E21>=500,4,IF(E21>=250,3,IF(E21>=100,2,1)))) | T21: =IF(F21>=1000,5,IF(F21>=500,4,IF(F21>=250,3,IF(F21>=100,2,1)))) | U21: =VLOOKUP(C21,Lookup_Tables!A:B,2,FALSE) | V21: =VLOOKUP(H21,Lookup_Tables!D:E,2,FALSE) | W21: =VLOOKUP(I21,Lookup_Tables!D:E,2,FALSE) | X21: =ROUND((D21*Controls!$B$4)+(G21*Controls!$B$5)+(K21*Controls!$B$6)+(L21*Controls!$B$7)+(M21*Controls!$B$8)+(MAX(N21,O21)*Controls!$B$9),2) | Y21: =IF(AND(C21="Bulk",F21>=Controls!$B$12),"A",IF(P21>=Controls!$B$10,"A",IF(P21>=Controls!$B$11,"B","C"))) | Z21: =IF(OR(D21>=4,G21>=4),1,IF(P21>=Controls!$B$11,2,3)) | AA21: =IF(OR(D21>=4,G21>=4),"Front",IF(P21>=Controls!$B$11,"Middle","Back")) | AB21: =Q21&R21&"-"&S21 | AC21: =IF(T21=J21,"Keep current slot","Re-slot for better access / flow")
A22: Premium A-Level Recommendations | B22: 4 | K22: =Controls!$B$22 | L22: =Controls!$B$20 | M22: =Controls!$B$21 | N22: =ROUND(K22*(L22/12)*(M22/12),2) | O22: =VLOOKUP(C22,Lookup_Tables!$G$4:$H$7,2,FALSE) | P22: =IF(O22<=N22,"Fits","Review") | Q22: =ROUND(O22/N22,3) | R22: =V22&W22&"-"&X22 | S22: =IF(E22>=1000,5,IF(E22>=500,4,IF(E22>=250,3,IF(E22>=100,2,1)))) | T22: =IF(F22>=1000,5,IF(F22>=500,4,IF(F22>=250,3,IF(F22>=100,2,1)))) | U22: =VLOOKUP(C22,Lookup_Tables!A:B,2,FALSE) | V22: =VLOOKUP(H22,Lookup_Tables!D:E,2,FALSE) | W22: =VLOOKUP(I22,Lookup_Tables!D:E,2,FALSE) | X22: =ROUND((D22*Controls!$B$4)+(G22*Controls!$B$5)+(K22*Controls!$B$6)+(L22*Controls!$B$7)+(M22*Controls!$B$8)+(MAX(N22,O22)*Controls!$B$9),2) | Y22: =IF(AND(C22="Bulk",F22>=Controls!$B$12),"A",IF(P22>=Controls!$B$10,"A",IF(P22>=Controls!$B$11,"B","C"))) | Z22: =IF(OR(D22>=4,G22>=4),1,IF(P22>=Controls!$B$11,2,3)) | AA22: =IF(OR(D22>=4,G22>=4),"Front",IF(P22>=Controls!$B$11,"Middle","Back")) | AB22: =Q22&R22&"-"&S22 | AC22: =IF(T22=J22,"Keep current slot","Re-slot for better access / flow")

Sheet Recommendations
A1: Recommendations (Updated with Cube Measurements)
A3: Priority | B3: Recommendation | C3: Rationale | D3: Expected Benefit
A4: High | B4: Convert repetitive Niagara water purchases to a contract-based cadence | C4: Validated water invoices show fixed quantity, price, and amount patterns across the period | D4: Reduce procurement effort and pursue 5%–12% savings
A5: High | B5: Reserve A-level front-access slots for high-usage and high-flow items | C5: Fast-moving staples and water should minimize handling and travel distance | D5: Improve picking speed and reduce congestion
A6: High | B6: Use GIK capacity increase for high-volume / high-velocity items | C6: GIK delivers the largest pallet-position gain after redesign | D6: Better cube utilization and simpler replenishment
A7: Medium | B7: Move slow-moving goods to C-level and back-depth slots | C7: Prime locations should not be consumed by low-flow items | D7: Free premium space for fast movers
A8: Medium | B8: Treat Kitchen separately because redesign improves security but reduces pallet positions | C8: Kitchen is a trade-off area, not a pure-capacity gain | D8: Protect operations while avoiding overloading this area
A12: • Cube-space dimensions were added to validate whether recommended locations are physically feasible.
A13: • High-priority items should not only be near flow paths, but must also fit the available cube volume.
A14: • Bulk/heavy items should remain on lower levels when quantity held is high, even if space is available elsewhere.
A16: • Peanut Butter was reclassified as a bulk, high-frequency item based on field notes and should be prioritized for lower/front storage.
A17: • Fresh / time-sensitive items should move quickly and should remain in fast-access locations to support the 3-day stay assumption.
A18: • Any item flagged as Manual Review in the final model should be checked against actual dimensions before final placement.
A20: • Final storage assignments now apply a capacity constraint so premium A-level/front space is reserved only for the highest-priority items.
A21: • GIK is prioritized for bulk and high-flow items, FOOD for staple food items, GARAGE/KITCHEN for reserve/support storage, and ADDITIONS for overflow bulk support.
A22: • The practical plan is intended to help SVDP re-slot materials in a phased and implementable way, not place every high-score item in the same premium zone.
A23: • Depth optimization is now applied so premium items are spread across A1, A2, and A3 instead of being concentrated in a single front-most slot.
A24: • Standard items are spread across B1, B2, and B3, while reserve items are spread across C1, C2, and C3.
A25: • This makes the storage plan more realistic, practical, and easier for the organization to implement.
... A31: • Storage_Reallocation_Plan and Slotting_Dashboard now both read directly from Hybrid_Location.

Sheet Clean_Transactions
A1: Clean Transactions
A3: Date | B3: Invoice/Doc | C3: Supplier | D3: Category | E3: Description | F3: Debit ($) | G3: Credit ($) | H3: Net ($)
A4: 45566 | B4: 218777 | C4: STAR FOODS INC. | D4: Food | E4: Bill - STAR FOODS INC.: Whole Kernal Corn NSA 24/15 oz. | F4: 28370.88 | H4: 28370.88
A5: 45570 | B5: 30658668 | C5: NIAGARA BOTTLING, LLC | D5: Water | E5: Bill - NIAGARA BOTTLING, LLC: Water | F5: 3561.6 | H5: 3561.6
A6: 45576 | B6: 3057986-IN | C6: GLOBAL FOODS INC. | D6: Food | E6: Bill - GLOBAL FOODS INC.: Creamy Peanut Butter | F6: 11777.6 | H6: 11777.6
A7: 45577 | B7: 30698733 | C7: NIAGARA BOTTLING, LLC | D7: Water | E7: Bill - NIAGARA BOTTLING, LLC: Water | F7: 3561.6 | H7: 3561.6
A8: 45583 | B8: 021000022924330 | C8: NIAGARA BOTTLING, LLC | D8: Exclude | E8: Excluded parser artifact – not a valid full Niagara invoice | F8: 0 | H8: 0
A9: 45584 | B9: 30733894 | C9: NIAGARA BOTTLING, LLC | D9: Water | E9: Bill - NIAGARA BOTTLING, LLC: Water | F9: 3561.6 | H9: 3561.6
A10: 45595 | B10: nan | C10: Unknown | D10: Food | E10: Reclass CIS Invoice 36978 | F10: 12543.6 | H10: 12543.6
A11: 45598 | B11: 30794368 | C11: NIAGARA BOTTLING, LLC | D11: Water | E11: Bill - NIAGARA BOTTLING, LLC: Water | F11: 3561.6 | H11: 3561.6
A12: 45600 | B12: 218822 | C12: STAR FOODS INC. | D12: Food | E12: Bill - STAR FOODS INC.: Dry Grocery Order | F12: 29590.28 | H12: 29590.28
A13: 45600 | B13: 218822 | C13: STAR FOODS INC. | D13: Food | E13: Bill - STAR FOODS INC.: Whole Kernal Corn NSA 24/15 oz. | F13: 1446.76 | H13: 1446.76
A14: 45612 | B14: 30852066 | C14: NIAGARA BOTTLING, LLC | D14: Water | E14: Bill - NIAGARA BOTTLING, LLC: 960 Cases @$3.71 | F14: 3561.6 | H14: 3561.6
A15: 45621 | B15: 218855 | C15: STAR FOODS INC. | D15: Food | E15: Bill - STAR FOODS INC.: Dry Grocery Order | F15: 35792.03 | H15: 35792.03
... A57: 45736 | B57: 51613 | C57: CIS, LLC | D57: Food | E57: Bill - CIS, LLC: Food items | F57: 30691.34 | H57: 30691.34

Sheet Water_Unique
A1: Deduplicated Water Invoices
A3: Date | B3: Invoice # | C3: Supplier | D3: Category | E3: Quantity | F3: Unit Price ($) | G3: Amount ($)
A4: 45682 | B4: 31212067 | C4: Niagara Bottling, LLC | D4: Water | E4: 960 | F4: 3.71 | G4: 3561.6
A5: 45702 | B5: 31298681 | C5: Niagara Bottling, LLC | D5: Water | E5: 960 | F5: 3.71 | G5: 3561.6
A6: 45710 | B6: 31361281 | C6: Niagara Bottling, LLC | D6: Water | E6: 960 | F6: 3.71 | G6: 3561.6
A7: 45724 | B7: 31492471 | C7: Niagara Bottling, LLC | D7: Water | E7: 960 | F7: 3.71 | G7: 3561.6
A8: 45738 | B8: 31631379 | C8: Niagara Bottling, LLC | D8: Water | E8: 960 | F8: 3.71 | G8: 3561.6
A9: 45738 | B9: 31632094 | C9: Niagara Bottling, LLC | D9: Water | E9: 960 | F9: 3.71 | G9: 3561.6
A10: 45745 | B10: 31695234 | C10: Niagara Bottling, LLC | D10: Water | E10: 960 | F10: 3.71 | G10: 3561.6
A11: 45808 | B11: 32261905 | C11: Niagara Bottling, LLC | D11: Water | E11: 960 | F11: 3.71 | G11: 3561.6
A12: 45822 | B12: 32416766 | C12: Niagara Bottling, LLC | D12: Water | E12: 960 | F12: 3.71 | G12: 3561.6
A13: 45836 | B13: 32542525 | C13: Niagara Bottling, LLC | D13: Water | E13: 960 | F13: 3.71 | G13: 3561.6
A14: 45864 | B14: 32748544 | C14: Niagara Bottling, LLC | D14: Water | E14: 960 | F14: 3.71 | G14: 3561.6
A15: 45878 | B15: 32916501 | C15: Niagara Bottling, LLC | D15: Water | E15: 960 | F15: 3.71 | G15: 3561.6
... A18: 45920 | B18: 33369264 | C18: Niagara Bottling, LLC | D18: Water | E18: 960 | F18: 3.71 | G18: 3561.6
A19: Total Orders | B19: =COUNTA(B4:B18) | G19: =SUM(G4:G18)

Sheet Raw_GL
A1: Raw General Ledger
A3: Posted dt. | B3: Doc dt. | C3: Doc | D3: Memo/Description | E3: Vendor name | F3: JNL | G3: Debit | H3: Credit | I3: Balance | J3: Net
A4: 45566 | B4: 45566 | C4: 218777 | D4: Bill - STAR FOODS INC.: Whole Kernal Corn NSA 24/15 oz. | E4: STAR FOODS INC. | F4: APJ | G4: 28370.88 | I4: 28370.88 | J4: 28370.88
A5: 45566 | B5: 45566 | C5: Reversed - | D5: Reversed -- FY24 Accrued Expenses - StarFoods | F5: GJ | H5: 28370.88 | I5: 0 | J5: -28370.88
A6: 45570 | B6: 45570 | C6: 30658668 | D6: Bill - NIAGARA BOTTLING, LLC: Water | E6: NIAGARA BOTTLING, LLC | F6: APJ | G6: 3561.6 | I6: 3561.6 | J6: 3561.6
A7: 45576 | B7: 45576 | C7: 3057986-IN | D7: Bill - GLOBAL FOODS INC.: Creamy Peanut Butter | E7: GLOBAL FOODS INC. | F7: APJ | G7: 11777.6 | I7: 15339.2 | J7: 11777.6
A8: 45577 | B8: 45577 | C8: 30698733 | D8: Bill - NIAGARA BOTTLING, LLC: Water | E8: NIAGARA BOTTLING, LLC | F8: APJ | G8: 3561.6 | I8: 18900.8 | J8: 3561.6
A9: 45583 | B9: 45583 | C9: 021000022924330 | D9: Bill - NIAGARA BOTTLING, LLC | E9: NIAGARA BOTTLING, LLC | F9: APJ | G9: 3.56 | I9: 18904.36 | J9: 3.56
A10: 45584 | B10: 45584 | C10: 30733894 | D10: Bill - NIAGARA BOTTLING, LLC: Water | E10: NIAGARA BOTTLING, LLC | F10: APJ | G10: 3561.6 | I10: 22465.96 | J10: 3561.6
A11: 45595 | B11: 45595 | D11: Reclass CIS Invoice 36978 | F11: GJ | G11: 12543.6 | I11: 35009.56 | J11: 12543.6
A12: 45598 | B12: 45598 | C12: 30794368 | D12: Bill - NIAGARA BOTTLING, LLC: Water | E12: NIAGARA BOTTLING, LLC | F12: APJ | G12: 3561.6 | I12: 38571.16 | J12: 3561.6
A13: 45600 | B13: 45600 | C13: 218822 | D13: Bill - STAR FOODS INC.: Dry Grocery Order | E13: STAR FOODS INC. | F13: APJ | G13: 29590.28 | I13: 68161.44 | J13: 29590.28
A14: 45600 | B14: 45600 | C14: 218822 | D14: Bill - STAR FOODS INC.: Whole Kernal Corn NSA 24/15 oz. | E14: STAR FOODS INC. | F14: APJ | G14: 1446.76 | I14: 69608.2 | J14: 1446.76
A15: 45612 | B15: 45612 | C15: 30852066 | D15: Bill - NIAGARA BOTTLING, LLC: 960 Cases @$3.71 | E15: NIAGARA BOTTLING, LLC | F15: APJ | G15: 3561.6 | I15: 73169.8 | J15: 3561.6
A16: 45621 | B16: 45621 | C16: 218855 | D16: Bill - STAR FOODS INC.: Dry Grocery Order | E16: STAR FOODS INC. | F16: APJ | G16: 35792.03 | I16: 108961.83 | J16: 35792.03
A17: 45621 | B17: 45621 | C17: 3058500-IN | D17: Bill - GLOBAL FOODS INC.: Kroger -Ground Beef 12/48 | E17: GLOBAL FOODS INC. | F17: APJ | G17: 9702 | I17: 118663.83 | J17: 9702
A18: 45626 | B18: 45626 | C18: 30903981 | D18: Bill - NIAGARA BOTTLING, LLC: 960 Cases @ $3.71 | E18: NIAGARA BOTTLING, LLC | F18: APJ | G18: 3561.6 | I18: 122225.43 | J18: 3561.6
A19: 45635 | B19: 45635 | C19: 3058597-IN | D19: Bill - GLOBAL FOODS INC.: Kroger -Ground Beef 80/20 & kroge | E19: GLOBAL FOODS INC. | F19: APJ | G19: 17404.8 | I19: 139630.23 | J19: 17404.8
A20: 45637 | B20: 45637 | C20: 3058631-IN | D20: Bill - GLOBAL FOODS INC.: Creamy Peanut Butter 12/18 oz | E20: GLOBAL FOODS INC. | F20: APJ | G20: 11777.6 | I20: 151407.83 | J20: 11777.6
A21: 45640 | B21: 45640 | C21: 30960939 | D21: Bill - NIAGARA BOTTLING, LLC: 960 Cases @ $3.71 | E21: NIAGARA BOTTLING, LLC | F21: APJ | G21: 3561.6 | I21: 154969.43 | J21: 3561.6
A22: 45646 | B22: 45646 | C22: 218867 | D22: Bill - STAR FOODS INC.: Food items/Groceries | E22: STAR FOODS INC. | F22: APJ | G22: 26168.52 | I22: 181137.95 | J22: 26168.52
A23: 45647 | B23: 45647 | C23: 30990822 | D23: Bill - NIAGARA BOTTLING, LLC | E23: NIAGARA BOTTLING, LLC | F23: APJ | G23: 3561.6 | I23: 184699.55 | J23: 3561.6
... A30: 45730 | B30: 45730 | C30: 219005 | D30: Bill - STAR FOODS INC.: Food items/Groceries | E30: STAR FOODS INC. | F30: APJ | G30: 33258.36 | I30: 279029.47 | J30: 33258.36
A31: 45736 | B31: 45736 | D31: Reclass CIS Invoice 51613 | F31: GJ | G31: 7456.44 | I31: 286485.91 | J31: 7456.44
A32: 45736 | B32: 45736 | D32: Reclass CIS Invoice 51613 | F32: GJ | G32: 23234.9 | I32: 309720.81 | J32: 23234.9
A33: 45737 | B33: 45737 | C33: Reversed - | D33: Reversed -- Reclass CIS Invoice 51613 | F33: GJ | H33: 7456.44 | I33: 302264.37 | J33: -7456.44
A34: 45737 | B34: 45737 | C34: Reversed - | D34: Reversed -- Reclass CIS Invoice 51613 | F34: GJ | H34: 23234.9 | I34: 279029.47 | J34: -23234.9
A35: 45738 | B35: 45738 | C35: 31631379 | D35: Bill - NIAGARA BOTTLING, LLC: NDW05L40PDRPBN 05L.DR.NIAGARA.40P.N.48.PB | E35: NIAGARA BOTTLING, LLC | F35: APJ | G35: 3561.6 | I35: 282591.07 | J35: 3561.6
A36: 45745 | B36: 45745 | C36: 31695234 | D36: Bill - NIAGARA BOTTLING, LLC: NDW05L40PDRPBN 05L.DR.NIAGARA.40P.N.48.PB | E36: NIAGARA BOTTLING, LLC | F36: APJ | G36: 3561.6 | I36: 286152.67 | J36: 3561.6
A37: 45748 | B37: 45748 | C37: 31492471 | D37: Bill - NIAGARA BOTTLING, LLC: NDW05L40PDRPBN 05L.DR.NIAGARA.40P.N.48.PB | E37: NIAGARA BOTTLING, LLC | F37: APJ | G37: 3561.6 | I37: 289714.27 | J37: 3561.6
A38: 45748 | B38: 45748 | C38: 31632094 | D38: Bill - NIAGARA BOTTLING, LLC: 960 Cases @ $3.71 | E38: NIAGARA BOTTLING, LLC | F38: APJ | G38: 3561.6 | I38: 293275.87 | J38: 3561.6
A39: 45748 | B39: 45748 | D39: APRIL GOOD CC; ALBERTSONS.COM #3204 877-505-4040, AZ-86403 ; water | F39: GJ | G39: 89.85 | I39: 293365.72 | J39: 89.85
A40: 45751 | B40: 45751 | C40: 219046 | D40: Bill - STAR FOODS INC.: Food items/Groceries | E40: STAR FOODS INC. | F40: APJ | G40: 33515.04 | I40: 326880.76 | J40: 33515.04
A41: 45757 | B41: 45757 | C41: 219047 | D41: Bill - STAR FOODS INC.: Food items/Groceries | E41: STAR FOODS INC. | F41: APJ | G41: 33515.04 | I41: 360395.8 | J41: 33515.04
A42: 45809 | B42: 45809 | C42: 32261905 | D42: Bill - NIAGARA BOTTLING, LLC: 960 Cases @ $3.71 | E42: NIAGARA BOTTLING, LLC | F42: APJ | G42: 3561.6 | I42: 363957.4 | J42: 3561.6
A43: 45813 | B43: 45813 | C43: 219103 | D43: Bill - STAR FOODS INC.: Food items/Groceries | E43: STAR FOODS INC. | F43: APJ | G43: 33515.04 | I43: 397472.44 | J43: 33515.04
A44: 45822 | B44: 45822 | C44: 32416766 | D44: Bill - NIAGARA BOTTLING, LLC: 960 Cases @ $3.71 | E44: NIAGARA BOTTLING, LLC | F44: APJ | G44: 3561.6 | I44: 401034.04 | J44: 3561.6
A45: 45839 | B45: 45839 | C45: 219140 | D45: Bill - STAR FOODS INC.: Food items/Groceries | E45: STAR FOODS INC. | F45: APJ | G45: 30336 | I45: 431370.04 | J45: 30336
A46: 45846 | B46: 45846 | C46: 32542525 | D46: Bill - NIAGARA BOTTLING, LLC: 05L.DR.NIAGARA.40P.N.48.CH | E46: NIAGARA BOTTLING, LLC | F46: APJ | G46: 684.8 | I46: 432054.84 | J46: 684.8
A47: 45846 | B47: 45846 | C47: 32542525 | D47: Bill - NIAGARA BOTTLING, LLC: 05L.DR.NIAGARA.40P.N.48.CH | E47: NIAGARA BOTTLING, LLC | F47: APJ | G47: 2876.8 | I47: 434931.64 | J47: 2876.8
A48: 45852 | B48: 45852 | C48: 219200 | D48: Bill - STAR FOODS INC.: Food items/Groceries | E48: STAR FOODS INC. | F48: APJ | G48: 33258.96 | I48: 468190.6 | J48: 33258.96
A49: 45859 | B49: 45859 | C49: 219201 | D49: Bill - STAR FOODS INC.: Food items/Groceries | E49: STAR FOODS INC. | F49: APJ | G49: 32767.92 | I49: 500958.52 | J49: 32767.92
A50: 45863 | B50: 45863 | C50: 219202 | D50: Bill - STAR FOODS INC.: Food items/Groceries | E50: STAR FOODS INC. | F50: APJ | G50: 32604.72 | I50: 533563.24 | J50: 32604.72
A51: 45864 | B51: 45864 | C51: 32748544 | D51: Bill - NIAGARA BOTTLING, LLC: 05L.DR.NIAGARA.40P.N.48.CH | E51: NIAGARA BOTTLING, LLC | F51: APJ | G51: 684.8 | I51: 534248.04 | J51: 684.8
... A58: 45922 | B58: 45922 | C58: 52946 | D58: Bill - CIS, LLC: Food items | E58: CIS, LLC | F58: APJ | G58: 23902.56 | I58: 605609.8 | J58: 23902.56
A59: 45930 | B59: 45930 | D59: Reclass CIS Invoice 51613 | F59: GJ | G59: 30691.34 | I59: 636301.14 | J59: 30691.34
A60: 45736 | B60: 45736 | C60: 51613 | D60: Bill - CIS, LLC: Food items | E60: CIS, LLC | F60: APJ | G60: 30691.34 | I60: 30691.34 | J60: 30691.34
A61: 45930 | B61: 45930 | D61: Reclass CIS Invoice 51613 | F61: GJ | H61: 30691.34 | I61: 0 | J61: -30691.34
